{"name": "smbg-fort - cthun-yogg-vf", "data": {"Phial_of_Static_Empowerment": {"3": 89678, "2": 89148, "1": 88629}, "Phial_of_Charged_Isolation": {"3": 89510, "2": 88980, "1": 88466}, "Phial_of_Tepid_Versatility": {"3": 87691, "2": 87488, "1": 87282}, "Iced_Phial_of_Corrupting_Rage": {"3": 87653, "2": 87395, "1": 87159}, "Phial_of_Elemental_Chaos": {"3": 87406, "2": 87221, "1": 87008}, "Phial_of_Glacial_Fury": {"3": 86520, "2": 86284, "1": 86009}, "Elemental_Potion_of_Ultimate_Power": {"3": 85439, "2": 85288, "1": 85236}, "Elemental_Potion_of_Power": {"3": 85195, "2": 85124, "1": 85055}, "Bottled_Putrescence": {"3": 85017, "2": 84996, "1": 84893}, "Potion_of_Shocking_Disclosure": {"3": 84983, "2": 84916, "1": 84842}, "Base": {"DPS": 84560}}, "ids": {"Phial_of_Static_Empowerment": 191338, "Phial_of_Charged_Isolation": 191332, "Phial_of_Tepid_Versatility": 191341, "Iced_Phial_of_Corrupting_Rage": 191329, "Phial_of_Elemental_Chaos": 191359, "Phial_of_Glacial_Fury": 191335, "Elemental_Potion_of_Ultimate_Power": 191383, "Elemental_Potion_of_Power": 191389, "Bottled_Putrescence": 191362, "Potion_of_Shocking_Disclosure": 191401}, "simulated_steps": [3, 2, 1], "sorted_data_keys": ["Phial_of_Static_Empowerment", "Phial_of_Charged_Isolation", "Phial_of_Tepid_Versatility", "Iced_Phial_of_Corrupting_Rage", "Phial_of_Elemental_Chaos", "Phial_of_Glacial_Fury", "Elemental_Potion_of_Ultimate_Power", "Elemental_Potion_of_Power", "Bottled_Putrescence", "Potion_of_Shocking_Disclosure"], "last_updated": "2023-02-14"}