{"name": "Composite - yshaarj-da", "data": {"Phial_of_Charged_Isolation": {"3": 102566, "2": 101810, "1": 101151}, "Phial_of_Static_Empowerment": {"3": 102289, "2": 101562, "1": 100949}, "Iced_Phial_of_Corrupting_Rage": {"3": 100158, "2": 99906, "1": 99645}, "Phial_of_Tepid_Versatility": {"3": 100055, "2": 99801, "1": 99541}, "Phial_of_Elemental_Chaos": {"3": 99880, "2": 99667, "1": 99439}, "Elemental_Potion_of_Ultimate_Power": {"3": 98459, "2": 98227, "1": 98027}, "Phial_of_Glacial_Fury": {"3": 98388, "2": 98147, "1": 97958}, "Elemental_Potion_of_Power": {"3": 98015, "2": 97863, "1": 97714}, "Bottled_Putrescence": {"3": 97467, "2": 97374, "1": 97310}, "Potion_of_Shocking_Disclosure": {"3": 97401, "2": 97342, "1": 97235}, "Base": {"DPS": 96788}}, "ids": {"Phial_of_Charged_Isolation": 191332, "Phial_of_Static_Empowerment": 191338, "Iced_Phial_of_Corrupting_Rage": 191329, "Phial_of_Tepid_Versatility": 191341, "Phial_of_Elemental_Chaos": 191359, "Elemental_Potion_of_Ultimate_Power": 191383, "Phial_of_Glacial_Fury": 191335, "Elemental_Potion_of_Power": 191389, "Bottled_Putrescence": 191362, "Potion_of_Shocking_Disclosure": 191401}, "simulated_steps": [3, 2, 1], "sorted_data_keys": ["Phial_of_Charged_Isolation", "Phial_of_Static_Empowerment", "Iced_Phial_of_Corrupting_Rage", "Phial_of_Tepid_Versatility", "Phial_of_Elemental_Chaos", "Elemental_Potion_of_Ultimate_Power", "Phial_of_Glacial_Fury", "Elemental_Potion_of_Power", "Bottled_Putrescence", "Potion_of_Shocking_Disclosure"], "last_updated": "2023-01-27"}