{"name": "neltharus-tyran - nzoth-cthun", "data": {"M4_V0_H6_C1": {"DPS": 137310}, "M4_V0_H5_C2": {"DPS": 137086}, "M3_V0_H6_C2": {"DPS": 137050}, "M5_V0_H5_C1": {"DPS": 137045}, "M5_V0_H6_C0": {"DPS": 136855}, "M5_V0_H4_C2": {"DPS": 136817}, "M3_V0_H5_C3": {"DPS": 136665}, "M4_V0_H4_C3": {"DPS": 136643}, "M4_V1_H5_C1": {"DPS": 136625}, "M3_V1_H6_C1": {"DPS": 136566}, "M4_V1_H4_C2": {"DPS": 136559}, "M4_V1_H6_C0": {"DPS": 136459}, "M3_V1_H5_C2": {"DPS": 136436}, "M5_V1_H4_C1": {"DPS": 136389}, "M5_V1_H5_C0": {"DPS": 136350}, "M2_V0_H6_C3": {"DPS": 136193}, "M3_V0_H7_C1": {"DPS": 136079}, "M3_V1_H4_C3": {"DPS": 136038}, "M2_V1_H6_C2": {"DPS": 136012}, "M6_V0_H4_C1": {"DPS": 135998}, "M3_V0_H4_C4": {"DPS": 135957}, "M4_V0_H7_C0": {"DPS": 135901}, "M3_V2_H5_C1": {"DPS": 135864}, "M6_V0_H5_C0": {"DPS": 135819}, "M4_V2_H4_C1": {"DPS": 135794}, "M4_V2_H5_C0": {"DPS": 135710}, "M2_V1_H5_C3": {"DPS": 135686}, "M3_V2_H4_C2": {"DPS": 135670}, "M3_V2_H6_C0": {"DPS": 135610}, "M2_V0_H5_C4": {"DPS": 135608}, "M2_V0_H7_C2": {"DPS": 135497}, "M5_V2_H4_C0": {"DPS": 135488}, "M2_V2_H6_C1": {"DPS": 135391}, "M5_V0_H3_C3": {"DPS": 135367}, "M6_V1_H4_C0": {"DPS": 135358}, "M2_V2_H5_C2": {"DPS": 135340}, "M3_V1_H7_C0": {"DPS": 135297}, "M5_V1_H3_C2": {"DPS": 135225}, "M4_V1_H3_C3": {"DPS": 135113}, "M2_V1_H7_C1": {"DPS": 135045}, "M4_V0_H3_C4": {"DPS": 135036}, "M2_V1_H4_C4": {"DPS": 134985}, "M2_V2_H4_C3": {"DPS": 134960}, "M3_V3_H4_C1": {"DPS": 134876}, "M6_V0_H3_C2": {"DPS": 134813}, "M1_V1_H6_C3": {"DPS": 134775}, "M4_V3_H4_C0": {"DPS": 134773}, "M4_V2_H3_C2": {"DPS": 134726}, "M2_V0_H4_C5": {"DPS": 134693}, "M3_V3_H5_C0": {"DPS": 134679}, "M7_V0_H4_C0": {"DPS": 134644}, "M1_V0_H6_C4": {"DPS": 134621}, "M5_V2_H3_C1": {"DPS": 134575}, "M3_V1_H3_C4": {"DPS": 134488}, "M2_V3_H5_C1": {"DPS": 134440}, "M1_V2_H6_C2": {"DPS": 134424}, "M3_V2_H3_C3": {"DPS": 134385}, "M6_V1_H3_C1": {"DPS": 134344}, "M2_V3_H4_C2": {"DPS": 134339}, "M1_V1_H5_C4": {"DPS": 134253}, "M3_V0_H8_C0": {"DPS": 134247}, "M1_V0_H7_C3": {"DPS": 134241}, "M2_V3_H6_C0": {"DPS": 134221}, "M1_V2_H5_C3": {"DPS": 134100}, "M3_V0_H3_C5": {"DPS": 134091}, "M2_V2_H7_C0": {"DPS": 134079}, "M1_V1_H7_C2": {"DPS": 134036}, "M2_V0_H8_C1": {"DPS": 133962}, "M1_V0_H5_C5": {"DPS": 133897}, "M4_V3_H3_C1": {"DPS": 133812}, "M3_V3_H3_C2": {"DPS": 133763}, "M2_V0_H9_C0": {"DPS": 133679}, "M7_V0_H3_C1": {"DPS": 133607}, "M1_V3_H6_C1": {"DPS": 133590}, "M1_V3_H5_C2": {"DPS": 133545}, "M3_V4_H4_C0": {"DPS": 133543}, "M5_V1_H2_C3": {"DPS": 133500}, "M5_V0_H2_C4": {"DPS": 133494}, "M1_V2_H4_C4": {"DPS": 133474}, "M1_V2_H7_C1": {"DPS": 133463}, "M1_V1_H4_C5": {"DPS": 133411}, "M5_V3_H3_C0": {"DPS": 133380}, "M6_V2_H3_C0": {"DPS": 133353}, "M2_V1_H8_C0": {"DPS": 133348}, "M2_V4_H4_C1": {"DPS": 133347}, "M2_V2_H3_C4": {"DPS": 133324}, "M4_V1_H2_C4": {"DPS": 133240}, "M2_V1_H3_C5": {"DPS": 133232}, "M5_V2_H2_C2": {"DPS": 133205}, "M1_V3_H4_C3": {"DPS": 133181}, "M2_V4_H5_C0": {"DPS": 133165}, "M1_V0_H8_C2": {"DPS": 133146}, "M6_V0_H2_C3": {"DPS": 133111}, "M4_V2_H2_C3": {"DPS": 133078}, "M2_V3_H3_C3": {"DPS": 133062}, "M0_V1_H6_C4": {"DPS": 132980}, "M1_V0_H9_C1": {"DPS": 132959}, "M7_V1_H3_C0": {"DPS": 132937}, "M6_V1_H2_C2": {"DPS": 132936}, "M4_V0_H2_C5": {"DPS": 132933}, "M0_V2_H6_C3": {"DPS": 132848}, "M1_V1_H8_C1": {"DPS": 132791}, "M3_V4_H3_C1": {"DPS": 132787}, "M0_V0_H6_C5": {"DPS": 132586}, "M1_V4_H5_C1": {"DPS": 132577}, "M4_V3_H2_C2": {"DPS": 132563}, "M4_V4_H3_C0": {"DPS": 132559}, "M3_V2_H2_C4": {"DPS": 132525}, "M1_V4_H4_C2": {"DPS": 132503}, "M0_V1_H7_C3": {"DPS": 132495}, "M1_V3_H7_C0": {"DPS": 132435}, "M0_V0_H7_C4": {"DPS": 132433}, "M6_V2_H2_C1": {"DPS": 132419}, "M1_V0_H4_C6": {"DPS": 132391}, "M5_V3_H2_C1": {"DPS": 132385}, "M3_V1_H2_C5": {"DPS": 132368}, "M0_V2_H5_C4": {"DPS": 132334}, "M2_V0_H3_C6": {"DPS": 132313}, "M1_V4_H6_C0": {"DPS": 132308}, "M7_V0_H2_C2": {"DPS": 132288}, "M1_V1_H9_C0": {"DPS": 132278}, "M0_V3_H6_C2": {"DPS": 132275}, "M2_V4_H3_C2": {"DPS": 132259}, "M0_V1_H5_C5": {"DPS": 132234}, "M3_V3_H2_C3": {"DPS": 132192}, "M0_V2_H7_C2": {"DPS": 132151}, "M0_V3_H5_C3": {"DPS": 132020}, "M2_V5_H4_C0": {"DPS": 131953}, "M1_V2_H8_C0": {"DPS": 131870}, "M1_V2_H3_C5": {"DPS": 131853}, "M7_V1_H2_C1": {"DPS": 131840}, "M8_V0_H3_C0": {"DPS": 131791}, "M1_V3_H3_C4": {"DPS": 131757}, "M5_V1_H1_C4": {"DPS": 131688}, "M4_V4_H2_C1": {"DPS": 131638}, "M0_V0_H8_C3": {"DPS": 131628}, "M3_V0_H2_C6": {"DPS": 131569}, "M0_V2_H4_C5": {"DPS": 131564}, "M5_V2_H1_C3": {"DPS": 131564}, "M0_V0_H9_C2": {"DPS": 131528}, "M0_V1_H8_C2": {"DPS": 131504}, "M0_V3_H7_C1": {"DPS": 131479}, "M3_V4_H2_C2": {"DPS": 131443}, "M0_V3_H4_C4": {"DPS": 131432}, "M5_V0_H1_C5": {"DPS": 131432}, "M2_V2_H2_C5": {"DPS": 131427}, "M6_V1_H1_C3": {"DPS": 131400}, "M1_V5_H4_C1": {"DPS": 131393}, "M0_V4_H6_C1": {"DPS": 131382}, "M2_V3_H2_C4": {"DPS": 131372}, "M0_V0_H5_C6": {"DPS": 131335}, "M6_V3_H2_C0": {"DPS": 131334}, "M3_V5_H3_C0": {"DPS": 131325}, "M0_V4_H5_C2": {"DPS": 131305}, "M4_V2_H1_C4": {"DPS": 131302}, "M6_V0_H1_C4": {"DPS": 131293}, "M5_V4_H2_C0": {"DPS": 131281}, "M4_V1_H1_C5": {"DPS": 131270}, "M2_V5_H3_C1": {"DPS": 131256}, "M1_V5_H5_C0": {"DPS": 131236}, "M1_V4_H3_C3": {"DPS": 131207}, "M0_V1_H9_C1": {"DPS": 131172}, "M1_V1_H3_C6": {"DPS": 131107}, "M5_V3_H1_C2": {"DPS": 131092}, "M7_V2_H2_C0": {"DPS": 131065}, "M6_V2_H1_C2": {"DPS": 131045}, "M0_V4_H4_C3": {"DPS": 130982}, "M4_V3_H1_C3": {"DPS": 130981}, "M0_V2_H8_C1": {"DPS": 130949}, "M2_V4_H2_C3": {"DPS": 130877}, "M8_V0_H2_C1": {"DPS": 130826}, "M0_V1_H4_C6": {"DPS": 130793}, "M7_V0_H1_C3": {"DPS": 130792}, "M2_V1_H2_C6": {"DPS": 130787}, "M1_V0_H10_C0": {"DPS": 130623}, "M7_V1_H1_C2": {"DPS": 130570}, "M3_V5_H2_C1": {"DPS": 130481}, "M0_V2_H9_C0": {"DPS": 130474}, "M3_V2_H1_C5": {"DPS": 130457}, "M1_V5_H3_C2": {"DPS": 130436}, "M3_V3_H1_C4": {"DPS": 130384}, "M4_V5_H2_C0": {"DPS": 130383}, "M4_V0_H1_C6": {"DPS": 130331}, "M0_V5_H5_C1": {"DPS": 130319}, "M4_V4_H1_C2": {"DPS": 130309}, "M0_V4_H7_C0": {"DPS": 130296}, "M6_V3_H1_C1": {"DPS": 130282}, "M8_V1_H2_C0": {"DPS": 130228}, "M5_V4_H1_C1": {"DPS": 130222}, "M0_V5_H4_C2": {"DPS": 130206}, "M2_V5_H2_C2": {"DPS": 130117}, "M1_V0_H3_C7": {"DPS": 130103}, "M7_V2_H1_C1": {"DPS": 130071}, "M0_V5_H6_C0": {"DPS": 130026}, "M1_V3_H2_C5": {"DPS": 129989}, "M0_V3_H8_C0": {"DPS": 129973}, "M0_V3_H3_C5": {"DPS": 129942}, "M3_V4_H1_C3": {"DPS": 129851}, "M3_V1_H1_C6": {"DPS": 129845}, "M0_V0_H4_C7": {"DPS": 129787}, "M1_V4_H2_C4": {"DPS": 129751}, "M2_V0_H2_C7": {"DPS": 129732}, "M5_V2_H0_C4": {"DPS": 129666}, "M0_V4_H3_C4": {"DPS": 129664}, "M5_V1_H0_C5": {"DPS": 129656}, "M1_V6_H4_C0": {"DPS": 129644}, "M8_V0_H1_C2": {"DPS": 129513}, "M1_V2_H2_C6": {"DPS": 129465}, "M0_V0_H10_C1": {"DPS": 129456}, "M6_V1_H0_C4": {"DPS": 129451}, "M0_V2_H3_C6": {"DPS": 129405}, "M5_V3_H0_C3": {"DPS": 129392}, "M2_V6_H3_C0": {"DPS": 129382}, "M2_V3_H1_C5": {"DPS": 129303}, "M6_V2_H0_C3": {"DPS": 129280}, "M4_V5_H1_C1": {"DPS": 129208}, "M6_V4_H1_C0": {"DPS": 129154}, "M4_V2_H0_C5": {"DPS": 129146}, "M6_V0_H0_C5": {"DPS": 129141}, "M8_V1_H1_C1": {"DPS": 129140}, "M0_V5_H3_C3": {"DPS": 129098}, "M1_V5_H2_C3": {"DPS": 129078}, "M2_V4_H1_C4": {"DPS": 129067}, "M3_V5_H1_C2": {"DPS": 129067}, "M7_V3_H1_C0": {"DPS": 129003}, "M4_V3_H0_C4": {"DPS": 128975}, "M9_V0_H2_C0": {"DPS": 128888}, "M1_V6_H3_C1": {"DPS": 128876}, "M7_V1_H0_C3": {"DPS": 128827}, "M5_V5_H1_C0": {"DPS": 128800}, "M0_V1_H10_C0": {"DPS": 128796}, "M2_V2_H1_C6": {"DPS": 128793}, "M6_V3_H0_C2": {"DPS": 128760}, "M7_V0_H0_C4": {"DPS": 128758}, "M5_V0_H0_C6": {"DPS": 128732}, "M3_V6_H2_C0": {"DPS": 128725}, "M3_V0_H1_C7": {"DPS": 128722}, "M0_V6_H4_C1": {"DPS": 128650}, "M5_V4_H0_C2": {"DPS": 128594}, "M1_V1_H2_C7": {"DPS": 128572}, "M2_V6_H2_C1": {"DPS": 128543}, "M4_V4_H0_C3": {"DPS": 128521}, "M0_V1_H3_C7": {"DPS": 128509}, "M0_V6_H5_C0": {"DPS": 128489}, "M7_V2_H0_C2": {"DPS": 128427}, "M2_V5_H1_C3": {"DPS": 128398}, "M4_V1_H0_C6": {"DPS": 128369}, "M8_V2_H1_C0": {"DPS": 128317}, "M3_V3_H0_C5": {"DPS": 128236}, "M2_V1_H1_C7": {"DPS": 127904}, "M3_V4_H0_C4": {"DPS": 127903}, "M0_V4_H2_C5": {"DPS": 127887}, "M6_V4_H0_C1": {"DPS": 127800}, "M7_V3_H0_C1": {"DPS": 127718}, "M3_V2_H0_C6": {"DPS": 127709}, "M1_V6_H2_C2": {"DPS": 127702}, "M9_V0_H1_C1": {"DPS": 127693}, "M4_V5_H0_C2": {"DPS": 127687}, "M8_V0_H0_C3": {"DPS": 127681}, "M0_V6_H3_C2": {"DPS": 127635}, "M1_V4_H1_C5": {"DPS": 127610}, "M8_V1_H0_C2": {"DPS": 127591}, "M5_V5_H0_C1": {"DPS": 127588}, "M3_V6_H1_C1": {"DPS": 127551}, "M0_V3_H2_C6": {"DPS": 127536}, "M0_V5_H2_C4": {"DPS": 127466}, "M4_V6_H1_C0": {"DPS": 127347}, "M4_V0_H0_C7": {"DPS": 127301}, "M3_V5_H0_C3": {"DPS": 127295}, "M1_V3_H1_C6": {"DPS": 127246}, "M9_V1_H1_C0": {"DPS": 127170}, "M1_V5_H1_C4": {"DPS": 127116}, "M2_V6_H1_C2": {"DPS": 127033}, "M0_V0_H11_C0": {"DPS": 126999}, "M8_V2_H0_C1": {"DPS": 126983}, "M1_V0_H2_C8": {"DPS": 126953}, "M0_V0_H3_C8": {"DPS": 126858}, "M2_V4_H0_C5": {"DPS": 126858}, "M1_V7_H3_C0": {"DPS": 126840}, "M3_V1_H0_C7": {"DPS": 126788}, "M0_V2_H2_C7": {"DPS": 126767}, "M0_V7_H4_C0": {"DPS": 126680}, "M1_V2_H1_C7": {"DPS": 126568}, "M7_V4_H0_C0": {"DPS": 126513}, "M2_V7_H2_C0": {"DPS": 126463}, "M6_V5_H0_C0": {"DPS": 126454}, "M2_V5_H0_C4": {"DPS": 126452}, "M2_V3_H0_C6": {"DPS": 126437}, "M2_V0_H1_C8": {"DPS": 126365}, "M0_V6_H2_C3": {"DPS": 126295}, "M9_V0_H0_C2": {"DPS": 126155}, "M4_V6_H0_C1": {"DPS": 126063}, "M1_V6_H1_C3": {"DPS": 126023}, "M0_V7_H3_C1": {"DPS": 126014}, "M1_V7_H2_C1": {"DPS": 126003}, "M8_V3_H0_C0": {"DPS": 125977}, "M3_V6_H0_C2": {"DPS": 125966}, "M9_V1_H0_C1": {"DPS": 125783}, "M2_V2_H0_C7": {"DPS": 125764}, "M5_V6_H0_C0": {"DPS": 125658}, "M3_V7_H1_C0": {"DPS": 125537}, "M10_V0_H1_C0": {"DPS": 125459}, "M2_V7_H1_C1": {"DPS": 125449}, "M0_V1_H2_C8": {"DPS": 125409}, "M0_V5_H1_C5": {"DPS": 125397}, "M3_V0_H0_C8": {"DPS": 125253}, "M2_V6_H0_C3": {"DPS": 125250}, "M1_V1_H1_C8": {"DPS": 125233}, "M0_V4_H1_C6": {"DPS": 125148}, "M9_V2_H0_C0": {"DPS": 125016}, "M1_V5_H0_C5": {"DPS": 125010}, "M1_V4_H0_C6": {"DPS": 124852}, "M0_V7_H2_C2": {"DPS": 124842}, "M0_V3_H1_C7": {"DPS": 124679}, "M1_V7_H1_C2": {"DPS": 124646}, "M0_V6_H1_C4": {"DPS": 124594}, "M2_V1_H0_C8": {"DPS": 124468}, "M3_V7_H0_C1": {"DPS": 124298}, "M1_V3_H0_C7": {"DPS": 124272}, "M4_V7_H0_C0": {"DPS": 124191}, "M10_V0_H0_C1": {"DPS": 124141}, "M1_V6_H0_C4": {"DPS": 124096}, "M2_V7_H0_C2": {"DPS": 123797}, "M1_V8_H2_C0": {"DPS": 123648}, "M0_V8_H3_C0": {"DPS": 123592}, "M0_V0_H2_C9": {"DPS": 123564}, "M10_V1_H0_C0": {"DPS": 123557}, "M0_V2_H1_C8": {"DPS": 123531}, "M1_V0_H1_C9": {"DPS": 123462}, "M0_V7_H1_C3": {"DPS": 123412}, "M2_V8_H1_C0": {"DPS": 123167}, "M1_V2_H0_C8": {"DPS": 123120}, "M1_V7_H0_C3": {"DPS": 123000}, "M0_V8_H2_C1": {"DPS": 122831}, "M0_V5_H0_C6": {"DPS": 122738}, "M1_V8_H1_C1": {"DPS": 122734}, "M2_V0_H0_C9": {"DPS": 122729}, "M0_V4_H0_C7": {"DPS": 122413}, "M0_V6_H0_C5": {"DPS": 122410}, "M0_V1_H1_C9": {"DPS": 122091}, "M3_V8_H0_C0": {"DPS": 122021}, "M2_V8_H0_C1": {"DPS": 121985}, "M11_V0_H0_C0": {"DPS": 121756}, "M0_V8_H1_C2": {"DPS": 121648}, "M1_V1_H0_C9": {"DPS": 121643}, "M0_V7_H0_C4": {"DPS": 121468}, "M0_V3_H0_C8": {"DPS": 121382}, "M1_V8_H0_C2": {"DPS": 121176}, "M0_V9_H2_C0": {"DPS": 120467}, "M1_V9_H1_C0": {"DPS": 120428}, "M0_V0_H1_C10": {"DPS": 120180}, "M0_V2_H0_C9": {"DPS": 120080}, "M0_V8_H0_C3": {"DPS": 119935}, "M1_V0_H0_C10": {"DPS": 119704}, "M2_V9_H0_C0": {"DPS": 119664}, "M0_V9_H1_C1": {"DPS": 119618}, "M1_V9_H0_C1": {"DPS": 119200}, "M0_V1_H0_C10": {"DPS": 118505}, "M0_V9_H0_C2": {"DPS": 118390}, "M0_V10_H1_C0": {"DPS": 117565}, "M1_V10_H0_C0": {"DPS": 117169}, "M0_V0_H0_C11": {"DPS": 116787}, "M0_V10_H0_C1": {"DPS": 116538}, "M0_V11_H0_C0": {"DPS": 114162}, "Base": {"DPS": 84544}}, "ids": {"M4_V0_H6_C1": null, "M4_V0_H5_C2": null, "M3_V0_H6_C2": null, "M5_V0_H5_C1": null, "M5_V0_H6_C0": null, "M5_V0_H4_C2": null, "M3_V0_H5_C3": null, "M4_V0_H4_C3": null, "M4_V1_H5_C1": null, "M3_V1_H6_C1": null, "M4_V1_H4_C2": null, "M4_V1_H6_C0": null, "M3_V1_H5_C2": null, "M5_V1_H4_C1": null, "M5_V1_H5_C0": null, "M2_V0_H6_C3": null, "M3_V0_H7_C1": null, "M3_V1_H4_C3": null, "M2_V1_H6_C2": null, "M6_V0_H4_C1": null, "M3_V0_H4_C4": null, "M4_V0_H7_C0": null, "M3_V2_H5_C1": null, "M6_V0_H5_C0": null, "M4_V2_H4_C1": null, "M4_V2_H5_C0": null, "M2_V1_H5_C3": null, "M3_V2_H4_C2": null, "M3_V2_H6_C0": null, "M2_V0_H5_C4": null, "M2_V0_H7_C2": null, "M5_V2_H4_C0": null, "M2_V2_H6_C1": null, "M5_V0_H3_C3": null, "M6_V1_H4_C0": null, "M2_V2_H5_C2": null, "M3_V1_H7_C0": null, "M5_V1_H3_C2": null, "M4_V1_H3_C3": null, "M2_V1_H7_C1": null, "M4_V0_H3_C4": null, "M2_V1_H4_C4": null, "M2_V2_H4_C3": null, "M3_V3_H4_C1": null, "M6_V0_H3_C2": null, "M1_V1_H6_C3": null, "M4_V3_H4_C0": null, "M4_V2_H3_C2": null, "M2_V0_H4_C5": null, "M3_V3_H5_C0": null, "M7_V0_H4_C0": null, "M1_V0_H6_C4": null, "M5_V2_H3_C1": null, "M3_V1_H3_C4": null, "M2_V3_H5_C1": null, "M1_V2_H6_C2": null, "M3_V2_H3_C3": null, "M6_V1_H3_C1": null, "M2_V3_H4_C2": null, "M1_V1_H5_C4": null, "M3_V0_H8_C0": null, "M1_V0_H7_C3": null, "M2_V3_H6_C0": null, "M1_V2_H5_C3": null, "M3_V0_H3_C5": null, "M2_V2_H7_C0": null, "M1_V1_H7_C2": null, "M2_V0_H8_C1": null, "M1_V0_H5_C5": null, "M4_V3_H3_C1": null, "M3_V3_H3_C2": null, "M2_V0_H9_C0": null, "M7_V0_H3_C1": null, "M1_V3_H6_C1": null, "M1_V3_H5_C2": null, "M3_V4_H4_C0": null, "M5_V1_H2_C3": null, "M5_V0_H2_C4": null, "M1_V2_H4_C4": null, "M1_V2_H7_C1": null, "M1_V1_H4_C5": null, "M5_V3_H3_C0": null, "M6_V2_H3_C0": null, "M2_V1_H8_C0": null, "M2_V4_H4_C1": null, "M2_V2_H3_C4": null, "M4_V1_H2_C4": null, "M2_V1_H3_C5": null, "M5_V2_H2_C2": null, "M1_V3_H4_C3": null, "M2_V4_H5_C0": null, "M1_V0_H8_C2": null, "M6_V0_H2_C3": null, "M4_V2_H2_C3": null, "M2_V3_H3_C3": null, "M0_V1_H6_C4": null, "M1_V0_H9_C1": null, "M7_V1_H3_C0": null, "M6_V1_H2_C2": null, "M4_V0_H2_C5": null, "M0_V2_H6_C3": null, "M1_V1_H8_C1": null, "M3_V4_H3_C1": null, "M0_V0_H6_C5": null, "M1_V4_H5_C1": null, "M4_V3_H2_C2": null, "M4_V4_H3_C0": null, "M3_V2_H2_C4": null, "M1_V4_H4_C2": null, "M0_V1_H7_C3": null, "M1_V3_H7_C0": null, "M0_V0_H7_C4": null, "M6_V2_H2_C1": null, "M1_V0_H4_C6": null, "M5_V3_H2_C1": null, "M3_V1_H2_C5": null, "M0_V2_H5_C4": null, "M2_V0_H3_C6": null, "M1_V4_H6_C0": null, "M7_V0_H2_C2": null, "M1_V1_H9_C0": null, "M0_V3_H6_C2": null, "M2_V4_H3_C2": null, "M0_V1_H5_C5": null, "M3_V3_H2_C3": null, "M0_V2_H7_C2": null, "M0_V3_H5_C3": null, "M2_V5_H4_C0": null, "M1_V2_H8_C0": null, "M1_V2_H3_C5": null, "M7_V1_H2_C1": null, "M8_V0_H3_C0": null, "M1_V3_H3_C4": null, "M5_V1_H1_C4": null, "M4_V4_H2_C1": null, "M0_V0_H8_C3": null, "M3_V0_H2_C6": null, "M0_V2_H4_C5": null, "M5_V2_H1_C3": null, "M0_V0_H9_C2": null, "M0_V1_H8_C2": null, "M0_V3_H7_C1": null, "M3_V4_H2_C2": null, "M0_V3_H4_C4": null, "M5_V0_H1_C5": null, "M2_V2_H2_C5": null, "M6_V1_H1_C3": null, "M1_V5_H4_C1": null, "M0_V4_H6_C1": null, "M2_V3_H2_C4": null, "M0_V0_H5_C6": null, "M6_V3_H2_C0": null, "M3_V5_H3_C0": null, "M0_V4_H5_C2": null, "M4_V2_H1_C4": null, "M6_V0_H1_C4": null, "M5_V4_H2_C0": null, "M4_V1_H1_C5": null, "M2_V5_H3_C1": null, "M1_V5_H5_C0": null, "M1_V4_H3_C3": null, "M0_V1_H9_C1": null, "M1_V1_H3_C6": null, "M5_V3_H1_C2": null, "M7_V2_H2_C0": null, "M6_V2_H1_C2": null, "M0_V4_H4_C3": null, "M4_V3_H1_C3": null, "M0_V2_H8_C1": null, "M2_V4_H2_C3": null, "M8_V0_H2_C1": null, "M0_V1_H4_C6": null, "M7_V0_H1_C3": null, "M2_V1_H2_C6": null, "M1_V0_H10_C0": null, "M7_V1_H1_C2": null, "M3_V5_H2_C1": null, "M0_V2_H9_C0": null, "M3_V2_H1_C5": null, "M1_V5_H3_C2": null, "M3_V3_H1_C4": null, "M4_V5_H2_C0": null, "M4_V0_H1_C6": null, "M0_V5_H5_C1": null, "M4_V4_H1_C2": null, "M0_V4_H7_C0": null, "M6_V3_H1_C1": null, "M8_V1_H2_C0": null, "M5_V4_H1_C1": null, "M0_V5_H4_C2": null, "M2_V5_H2_C2": null, "M1_V0_H3_C7": null, "M7_V2_H1_C1": null, "M0_V5_H6_C0": null, "M1_V3_H2_C5": null, "M0_V3_H8_C0": null, "M0_V3_H3_C5": null, "M3_V4_H1_C3": null, "M3_V1_H1_C6": null, "M0_V0_H4_C7": null, "M1_V4_H2_C4": null, "M2_V0_H2_C7": null, "M5_V2_H0_C4": null, "M0_V4_H3_C4": null, "M5_V1_H0_C5": null, "M1_V6_H4_C0": null, "M8_V0_H1_C2": null, "M1_V2_H2_C6": null, "M0_V0_H10_C1": null, "M6_V1_H0_C4": null, "M0_V2_H3_C6": null, "M5_V3_H0_C3": null, "M2_V6_H3_C0": null, "M2_V3_H1_C5": null, "M6_V2_H0_C3": null, "M4_V5_H1_C1": null, "M6_V4_H1_C0": null, "M4_V2_H0_C5": null, "M6_V0_H0_C5": null, "M8_V1_H1_C1": null, "M0_V5_H3_C3": null, "M1_V5_H2_C3": null, "M2_V4_H1_C4": null, "M3_V5_H1_C2": null, "M7_V3_H1_C0": null, "M4_V3_H0_C4": null, "M9_V0_H2_C0": null, "M1_V6_H3_C1": null, "M7_V1_H0_C3": null, "M5_V5_H1_C0": null, "M0_V1_H10_C0": null, "M2_V2_H1_C6": null, "M6_V3_H0_C2": null, "M7_V0_H0_C4": null, "M5_V0_H0_C6": null, "M3_V6_H2_C0": null, "M3_V0_H1_C7": null, "M0_V6_H4_C1": null, "M5_V4_H0_C2": null, "M1_V1_H2_C7": null, "M2_V6_H2_C1": null, "M4_V4_H0_C3": null, "M0_V1_H3_C7": null, "M0_V6_H5_C0": null, "M7_V2_H0_C2": null, "M2_V5_H1_C3": null, "M4_V1_H0_C6": null, "M8_V2_H1_C0": null, "M3_V3_H0_C5": null, "M2_V1_H1_C7": null, "M3_V4_H0_C4": null, "M0_V4_H2_C5": null, "M6_V4_H0_C1": null, "M7_V3_H0_C1": null, "M3_V2_H0_C6": null, "M1_V6_H2_C2": null, "M9_V0_H1_C1": null, "M4_V5_H0_C2": null, "M8_V0_H0_C3": null, "M0_V6_H3_C2": null, "M1_V4_H1_C5": null, "M8_V1_H0_C2": null, "M5_V5_H0_C1": null, "M3_V6_H1_C1": null, "M0_V3_H2_C6": null, "M0_V5_H2_C4": null, "M4_V6_H1_C0": null, "M4_V0_H0_C7": null, "M3_V5_H0_C3": null, "M1_V3_H1_C6": null, "M9_V1_H1_C0": null, "M1_V5_H1_C4": null, "M2_V6_H1_C2": null, "M0_V0_H11_C0": null, "M8_V2_H0_C1": null, "M1_V0_H2_C8": null, "M0_V0_H3_C8": null, "M2_V4_H0_C5": null, "M1_V7_H3_C0": null, "M3_V1_H0_C7": null, "M0_V2_H2_C7": null, "M0_V7_H4_C0": null, "M1_V2_H1_C7": null, "M7_V4_H0_C0": null, "M2_V7_H2_C0": null, "M6_V5_H0_C0": null, "M2_V5_H0_C4": null, "M2_V3_H0_C6": null, "M2_V0_H1_C8": null, "M0_V6_H2_C3": null, "M9_V0_H0_C2": null, "M4_V6_H0_C1": null, "M1_V6_H1_C3": null, "M0_V7_H3_C1": null, "M1_V7_H2_C1": null, "M8_V3_H0_C0": null, "M3_V6_H0_C2": null, "M9_V1_H0_C1": null, "M2_V2_H0_C7": null, "M5_V6_H0_C0": null, "M3_V7_H1_C0": null, "M10_V0_H1_C0": null, "M2_V7_H1_C1": null, "M0_V1_H2_C8": null, "M0_V5_H1_C5": null, "M3_V0_H0_C8": null, "M2_V6_H0_C3": null, "M1_V1_H1_C8": null, "M0_V4_H1_C6": null, "M9_V2_H0_C0": null, "M1_V5_H0_C5": null, "M1_V4_H0_C6": null, "M0_V7_H2_C2": null, "M0_V3_H1_C7": null, "M1_V7_H1_C2": null, "M0_V6_H1_C4": null, "M2_V1_H0_C8": null, "M3_V7_H0_C1": null, "M1_V3_H0_C7": null, "M4_V7_H0_C0": null, "M10_V0_H0_C1": null, "M1_V6_H0_C4": null, "M2_V7_H0_C2": null, "M1_V8_H2_C0": null, "M0_V8_H3_C0": null, "M0_V0_H2_C9": null, "M10_V1_H0_C0": null, "M0_V2_H1_C8": null, "M1_V0_H1_C9": null, "M0_V7_H1_C3": null, "M2_V8_H1_C0": null, "M1_V2_H0_C8": null, "M1_V7_H0_C3": null, "M0_V8_H2_C1": null, "M0_V5_H0_C6": null, "M1_V8_H1_C1": null, "M2_V0_H0_C9": null, "M0_V4_H0_C7": null, "M0_V6_H0_C5": null, "M0_V1_H1_C9": null, "M3_V8_H0_C0": null, "M2_V8_H0_C1": null, "M11_V0_H0_C0": null, "M0_V8_H1_C2": null, "M1_V1_H0_C9": null, "M0_V7_H0_C4": null, "M0_V3_H0_C8": null, "M1_V8_H0_C2": null, "M0_V9_H2_C0": null, "M1_V9_H1_C0": null, "M0_V0_H1_C10": null, "M0_V2_H0_C9": null, "M0_V8_H0_C3": null, "M1_V0_H0_C10": null, "M2_V9_H0_C0": null, "M0_V9_H1_C1": null, "M1_V9_H0_C1": null, "M0_V1_H0_C10": null, "M0_V9_H0_C2": null, "M0_V10_H1_C0": null, "M1_V10_H0_C0": null, "M0_V0_H0_C11": null, "M0_V10_H0_C1": null, "M0_V11_H0_C0": null}, "simulated_steps": ["DPS"], "sorted_data_keys": ["M4_V0_H6_C1", "M4_V0_H5_C2", "M3_V0_H6_C2", "M5_V0_H5_C1", "M5_V0_H6_C0", "M5_V0_H4_C2", "M3_V0_H5_C3", "M4_V0_H4_C3", "M4_V1_H5_C1", "M3_V1_H6_C1", "M4_V1_H4_C2", "M4_V1_H6_C0", "M3_V1_H5_C2", "M5_V1_H4_C1", "M5_V1_H5_C0", "M2_V0_H6_C3", "M3_V0_H7_C1", "M3_V1_H4_C3", "M2_V1_H6_C2", "M6_V0_H4_C1", "M3_V0_H4_C4", "M4_V0_H7_C0", "M3_V2_H5_C1", "M6_V0_H5_C0", "M4_V2_H4_C1", "M4_V2_H5_C0", "M2_V1_H5_C3", "M3_V2_H4_C2", "M3_V2_H6_C0", "M2_V0_H5_C4", "M2_V0_H7_C2", "M5_V2_H4_C0", "M2_V2_H6_C1", "M5_V0_H3_C3", "M6_V1_H4_C0", "M2_V2_H5_C2", "M3_V1_H7_C0", "M5_V1_H3_C2", "M4_V1_H3_C3", "M2_V1_H7_C1", "M4_V0_H3_C4", "M2_V1_H4_C4", "M2_V2_H4_C3", "M3_V3_H4_C1", "M6_V0_H3_C2", "M1_V1_H6_C3", "M4_V3_H4_C0", "M4_V2_H3_C2", "M2_V0_H4_C5", "M3_V3_H5_C0", "M7_V0_H4_C0", "M1_V0_H6_C4", "M5_V2_H3_C1", "M3_V1_H3_C4", "M2_V3_H5_C1", "M1_V2_H6_C2", "M3_V2_H3_C3", "M6_V1_H3_C1", "M2_V3_H4_C2", "M1_V1_H5_C4", "M3_V0_H8_C0", "M1_V0_H7_C3", "M2_V3_H6_C0", "M1_V2_H5_C3", "M3_V0_H3_C5", "M2_V2_H7_C0", "M1_V1_H7_C2", "M2_V0_H8_C1", "M1_V0_H5_C5", "M4_V3_H3_C1", "M3_V3_H3_C2", "M2_V0_H9_C0", "M7_V0_H3_C1", "M1_V3_H6_C1", "M1_V3_H5_C2", "M3_V4_H4_C0", "M5_V1_H2_C3", "M5_V0_H2_C4", "M1_V2_H4_C4", "M1_V2_H7_C1", "M1_V1_H4_C5", "M5_V3_H3_C0", "M6_V2_H3_C0", "M2_V1_H8_C0", "M2_V4_H4_C1", "M2_V2_H3_C4", "M4_V1_H2_C4", "M2_V1_H3_C5", "M5_V2_H2_C2", "M1_V3_H4_C3", "M2_V4_H5_C0", "M1_V0_H8_C2", "M6_V0_H2_C3", "M4_V2_H2_C3", "M2_V3_H3_C3", "M0_V1_H6_C4", "M1_V0_H9_C1", "M7_V1_H3_C0", "M6_V1_H2_C2", "M4_V0_H2_C5", "M0_V2_H6_C3", "M1_V1_H8_C1", "M3_V4_H3_C1", "M0_V0_H6_C5", "M1_V4_H5_C1", "M4_V3_H2_C2", "M4_V4_H3_C0", "M3_V2_H2_C4", "M1_V4_H4_C2", "M0_V1_H7_C3", "M1_V3_H7_C0", "M0_V0_H7_C4", "M6_V2_H2_C1", "M1_V0_H4_C6", "M5_V3_H2_C1", "M3_V1_H2_C5", "M0_V2_H5_C4", "M2_V0_H3_C6", "M1_V4_H6_C0", "M7_V0_H2_C2", "M1_V1_H9_C0", "M0_V3_H6_C2", "M2_V4_H3_C2", "M0_V1_H5_C5", "M3_V3_H2_C3", "M0_V2_H7_C2", "M0_V3_H5_C3", "M2_V5_H4_C0", "M1_V2_H8_C0", "M1_V2_H3_C5", "M7_V1_H2_C1", "M8_V0_H3_C0", "M1_V3_H3_C4", "M5_V1_H1_C4", "M4_V4_H2_C1", "M0_V0_H8_C3", "M3_V0_H2_C6", "M0_V2_H4_C5", "M5_V2_H1_C3", "M0_V0_H9_C2", "M0_V1_H8_C2", "M0_V3_H7_C1", "M3_V4_H2_C2", "M0_V3_H4_C4", "M5_V0_H1_C5", "M2_V2_H2_C5", "M6_V1_H1_C3", "M1_V5_H4_C1", "M0_V4_H6_C1", "M2_V3_H2_C4", "M0_V0_H5_C6", "M6_V3_H2_C0", "M3_V5_H3_C0", "M0_V4_H5_C2", "M4_V2_H1_C4", "M6_V0_H1_C4", "M5_V4_H2_C0", "M4_V1_H1_C5", "M2_V5_H3_C1", "M1_V5_H5_C0", "M1_V4_H3_C3", "M0_V1_H9_C1", "M1_V1_H3_C6", "M5_V3_H1_C2", "M7_V2_H2_C0", "M6_V2_H1_C2", "M0_V4_H4_C3", "M4_V3_H1_C3", "M0_V2_H8_C1", "M2_V4_H2_C3", "M8_V0_H2_C1", "M0_V1_H4_C6", "M7_V0_H1_C3", "M2_V1_H2_C6", "M1_V0_H10_C0", "M7_V1_H1_C2", "M3_V5_H2_C1", "M0_V2_H9_C0", "M3_V2_H1_C5", "M1_V5_H3_C2", "M3_V3_H1_C4", "M4_V5_H2_C0", "M4_V0_H1_C6", "M0_V5_H5_C1", "M4_V4_H1_C2", "M0_V4_H7_C0", "M6_V3_H1_C1", "M8_V1_H2_C0", "M5_V4_H1_C1", "M0_V5_H4_C2", "M2_V5_H2_C2", "M1_V0_H3_C7", "M7_V2_H1_C1", "M0_V5_H6_C0", "M1_V3_H2_C5", "M0_V3_H8_C0", "M0_V3_H3_C5", "M3_V4_H1_C3", "M3_V1_H1_C6", "M0_V0_H4_C7", "M1_V4_H2_C4", "M2_V0_H2_C7", "M5_V2_H0_C4", "M0_V4_H3_C4", "M5_V1_H0_C5", "M1_V6_H4_C0", "M8_V0_H1_C2", "M1_V2_H2_C6", "M0_V0_H10_C1", "M6_V1_H0_C4", "M0_V2_H3_C6", "M5_V3_H0_C3", "M2_V6_H3_C0", "M2_V3_H1_C5", "M6_V2_H0_C3", "M4_V5_H1_C1", "M6_V4_H1_C0", "M4_V2_H0_C5", "M6_V0_H0_C5", "M8_V1_H1_C1", "M0_V5_H3_C3", "M1_V5_H2_C3", "M2_V4_H1_C4", "M3_V5_H1_C2", "M7_V3_H1_C0", "M4_V3_H0_C4", "M9_V0_H2_C0", "M1_V6_H3_C1", "M7_V1_H0_C3", "M5_V5_H1_C0", "M0_V1_H10_C0", "M2_V2_H1_C6", "M6_V3_H0_C2", "M7_V0_H0_C4", "M5_V0_H0_C6", "M3_V6_H2_C0", "M3_V0_H1_C7", "M0_V6_H4_C1", "M5_V4_H0_C2", "M1_V1_H2_C7", "M2_V6_H2_C1", "M4_V4_H0_C3", "M0_V1_H3_C7", "M0_V6_H5_C0", "M7_V2_H0_C2", "M2_V5_H1_C3", "M4_V1_H0_C6", "M8_V2_H1_C0", "M3_V3_H0_C5", "M2_V1_H1_C7", "M3_V4_H0_C4", "M0_V4_H2_C5", "M6_V4_H0_C1", "M7_V3_H0_C1", "M3_V2_H0_C6", "M1_V6_H2_C2", "M9_V0_H1_C1", "M4_V5_H0_C2", "M8_V0_H0_C3", "M0_V6_H3_C2", "M1_V4_H1_C5", "M8_V1_H0_C2", "M5_V5_H0_C1", "M3_V6_H1_C1", "M0_V3_H2_C6", "M0_V5_H2_C4", "M4_V6_H1_C0", "M4_V0_H0_C7", "M3_V5_H0_C3", "M1_V3_H1_C6", "M9_V1_H1_C0", "M1_V5_H1_C4", "M2_V6_H1_C2", "M0_V0_H11_C0", "M8_V2_H0_C1", "M1_V0_H2_C8", "M0_V0_H3_C8", "M2_V4_H0_C5", "M1_V7_H3_C0", "M3_V1_H0_C7", "M0_V2_H2_C7", "M0_V7_H4_C0", "M1_V2_H1_C7", "M7_V4_H0_C0", "M2_V7_H2_C0", "M6_V5_H0_C0", "M2_V5_H0_C4", "M2_V3_H0_C6", "M2_V0_H1_C8", "M0_V6_H2_C3", "M9_V0_H0_C2", "M4_V6_H0_C1", "M1_V6_H1_C3", "M0_V7_H3_C1", "M1_V7_H2_C1", "M8_V3_H0_C0", "M3_V6_H0_C2", "M9_V1_H0_C1", "M2_V2_H0_C7", "M5_V6_H0_C0", "M3_V7_H1_C0", "M10_V0_H1_C0", "M2_V7_H1_C1", "M0_V1_H2_C8", "M0_V5_H1_C5", "M3_V0_H0_C8", "M2_V6_H0_C3", "M1_V1_H1_C8", "M0_V4_H1_C6", "M9_V2_H0_C0", "M1_V5_H0_C5", "M1_V4_H0_C6", "M0_V7_H2_C2", "M0_V3_H1_C7", "M1_V7_H1_C2", "M0_V6_H1_C4", "M2_V1_H0_C8", "M3_V7_H0_C1", "M1_V3_H0_C7", "M4_V7_H0_C0", "M10_V0_H0_C1", "M1_V6_H0_C4", "M2_V7_H0_C2", "M1_V8_H2_C0", "M0_V8_H3_C0", "M0_V0_H2_C9", "M10_V1_H0_C0", "M0_V2_H1_C8", "M1_V0_H1_C9", "M0_V7_H1_C3", "M2_V8_H1_C0", "M1_V2_H0_C8", "M1_V7_H0_C3", "M0_V8_H2_C1", "M0_V5_H0_C6", "M1_V8_H1_C1", "M2_V0_H0_C9", "M0_V4_H0_C7", "M0_V6_H0_C5", "M0_V1_H1_C9", "M3_V8_H0_C0", "M2_V8_H0_C1", "M11_V0_H0_C0", "M0_V8_H1_C2", "M1_V1_H0_C9", "M0_V7_H0_C4", "M0_V3_H0_C8", "M1_V8_H0_C2", "M0_V9_H2_C0", "M1_V9_H1_C0", "M0_V0_H1_C10", "M0_V2_H0_C9", "M0_V8_H0_C3", "M1_V0_H0_C10", "M2_V9_H0_C0", "M0_V9_H1_C1", "M1_V9_H0_C1", "M0_V1_H0_C10", "M0_V9_H0_C2", "M0_V10_H1_C0", "M1_V10_H0_C0", "M0_V0_H0_C11", "M0_V10_H0_C1", "M0_V11_H0_C0"], "last_updated": "2023-05-06"}