{"name": "algethar-tyran - nzoth-yogg-vf", "data": {"M5_V0_H7_C0": {"DPS": 73039}, "M4_V0_H8_C0": {"DPS": 72974}, "M4_V0_H7_C1": {"DPS": 72856}, "M3_V0_H9_C0": {"DPS": 72784}, "M6_V0_H6_C0": {"DPS": 72739}, "M4_V1_H7_C0": {"DPS": 72730}, "M3_V0_H8_C1": {"DPS": 72726}, "M5_V0_H6_C1": {"DPS": 72654}, "M3_V1_H8_C0": {"DPS": 72625}, "M3_V0_H7_C2": {"DPS": 72540}, "M5_V1_H6_C0": {"DPS": 72514}, "M3_V1_H7_C1": {"DPS": 72478}, "M4_V0_H6_C2": {"DPS": 72384}, "M2_V0_H9_C1": {"DPS": 72352}, "M3_V2_H7_C0": {"DPS": 72311}, "M4_V1_H6_C1": {"DPS": 72310}, "M2_V1_H9_C0": {"DPS": 72278}, "M2_V0_H8_C2": {"DPS": 72258}, "M2_V1_H8_C1": {"DPS": 72222}, "M4_V2_H6_C0": {"DPS": 72160}, "M6_V0_H5_C1": {"DPS": 72121}, "M7_V0_H5_C0": {"DPS": 72088}, "M2_V2_H8_C0": {"DPS": 72041}, "M2_V1_H7_C2": {"DPS": 72030}, "M3_V1_H6_C2": {"DPS": 72005}, "M2_V0_H7_C3": {"DPS": 71986}, "M2_V0_H10_C0": {"DPS": 71983}, "M6_V1_H5_C0": {"DPS": 71972}, "M3_V0_H6_C3": {"DPS": 71962}, "M2_V2_H7_C1": {"DPS": 71939}, "M5_V0_H5_C2": {"DPS": 71900}, "M5_V1_H5_C1": {"DPS": 71873}, "M3_V2_H6_C1": {"DPS": 71871}, "M1_V1_H9_C1": {"DPS": 71764}, "M1_V0_H9_C2": {"DPS": 71761}, "M5_V2_H5_C0": {"DPS": 71711}, "M2_V3_H7_C0": {"DPS": 71657}, "M4_V1_H5_C2": {"DPS": 71648}, "M1_V1_H8_C2": {"DPS": 71646}, "M3_V3_H6_C0": {"DPS": 71646}, "M1_V0_H8_C3": {"DPS": 71607}, "M4_V0_H5_C3": {"DPS": 71582}, "M1_V2_H9_C0": {"DPS": 71567}, "M1_V2_H8_C1": {"DPS": 71540}, "M4_V2_H5_C1": {"DPS": 71521}, "M2_V2_H6_C2": {"DPS": 71471}, "M1_V0_H10_C1": {"DPS": 71449}, "M7_V0_H4_C1": {"DPS": 71445}, "M2_V1_H6_C3": {"DPS": 71436}, "M1_V0_H11_C0": {"DPS": 71397}, "M6_V0_H4_C2": {"DPS": 71366}, "M7_V1_H4_C0": {"DPS": 71360}, "M2_V0_H6_C4": {"DPS": 71350}, "M1_V1_H7_C3": {"DPS": 71334}, "M1_V2_H7_C2": {"DPS": 71320}, "M6_V1_H4_C1": {"DPS": 71312}, "M1_V1_H10_C0": {"DPS": 71308}, "M1_V3_H8_C0": {"DPS": 71297}, "M4_V3_H5_C0": {"DPS": 71294}, "M2_V3_H6_C1": {"DPS": 71288}, "M1_V0_H7_C4": {"DPS": 71245}, "M3_V1_H5_C3": {"DPS": 71205}, "M8_V0_H4_C0": {"DPS": 71199}, "M6_V2_H4_C0": {"DPS": 71173}, "M3_V2_H5_C2": {"DPS": 71170}, "M1_V3_H7_C1": {"DPS": 71162}, "M5_V1_H4_C2": {"DPS": 71154}, "M5_V0_H4_C3": {"DPS": 71121}, "M3_V0_H5_C4": {"DPS": 71104}, "M5_V2_H4_C1": {"DPS": 71068}, "M3_V3_H5_C1": {"DPS": 71036}, "M0_V1_H9_C2": {"DPS": 71033}, "M0_V0_H9_C3": {"DPS": 71016}, "M2_V4_H6_C0": {"DPS": 70960}, "M0_V2_H9_C1": {"DPS": 70938}, "M4_V1_H4_C3": {"DPS": 70874}, "M0_V1_H8_C3": {"DPS": 70863}, "M5_V3_H4_C0": {"DPS": 70852}, "M0_V2_H8_C2": {"DPS": 70843}, "M1_V2_H6_C3": {"DPS": 70837}, "M1_V4_H7_C0": {"DPS": 70837}, "M4_V2_H4_C2": {"DPS": 70824}, "M4_V0_H4_C4": {"DPS": 70786}, "M0_V0_H8_C4": {"DPS": 70783}, "M1_V1_H6_C4": {"DPS": 70783}, "M0_V0_H10_C2": {"DPS": 70746}, "M0_V0_H11_C1": {"DPS": 70744}, "M1_V3_H6_C2": {"DPS": 70734}, "M0_V1_H10_C1": {"DPS": 70711}, "M0_V3_H8_C1": {"DPS": 70709}, "M0_V3_H9_C0": {"DPS": 70703}, "M0_V1_H11_C0": {"DPS": 70683}, "M3_V4_H5_C0": {"DPS": 70681}, "M2_V2_H5_C3": {"DPS": 70678}, "M7_V0_H3_C2": {"DPS": 70662}, "M4_V3_H4_C1": {"DPS": 70660}, "M2_V1_H5_C4": {"DPS": 70655}, "M1_V0_H6_C5": {"DPS": 70631}, "M7_V1_H3_C1": {"DPS": 70610}, "M2_V3_H5_C2": {"DPS": 70584}, "M0_V2_H10_C0": {"DPS": 70581}, "M0_V2_H7_C3": {"DPS": 70544}, "M0_V1_H7_C4": {"DPS": 70535}, "M6_V1_H3_C2": {"DPS": 70533}, "M6_V0_H3_C3": {"DPS": 70498}, "M1_V4_H6_C1": {"DPS": 70493}, "M2_V0_H5_C5": {"DPS": 70482}, "M0_V3_H7_C2": {"DPS": 70467}, "M3_V2_H4_C3": {"DPS": 70461}, "M3_V1_H4_C4": {"DPS": 70444}, "M8_V0_H3_C1": {"DPS": 70430}, "M4_V4_H4_C0": {"DPS": 70429}, "M7_V2_H3_C0": {"DPS": 70421}, "M6_V2_H3_C1": {"DPS": 70417}, "M0_V4_H8_C0": {"DPS": 70413}, "M0_V0_H7_C5": {"DPS": 70394}, "M2_V4_H5_C1": {"DPS": 70383}, "M8_V1_H3_C0": {"DPS": 70382}, "M3_V3_H4_C2": {"DPS": 70372}, "M3_V0_H4_C5": {"DPS": 70328}, "M5_V2_H3_C2": {"DPS": 70319}, "M5_V1_H3_C3": {"DPS": 70304}, "M0_V4_H7_C1": {"DPS": 70277}, "M6_V3_H3_C0": {"DPS": 70257}, "M0_V0_H12_C0": {"DPS": 70250}, "M5_V0_H3_C4": {"DPS": 70232}, "M3_V4_H4_C1": {"DPS": 70197}, "M1_V5_H6_C0": {"DPS": 70194}, "M5_V3_H3_C1": {"DPS": 70164}, "M9_V0_H3_C0": {"DPS": 70126}, "M0_V2_H6_C4": {"DPS": 70098}, "M2_V5_H5_C0": {"DPS": 70052}, "M1_V2_H5_C4": {"DPS": 70027}, "M0_V3_H6_C3": {"DPS": 70010}, "M2_V2_H4_C4": {"DPS": 70008}, "M0_V1_H6_C5": {"DPS": 70004}, "M1_V3_H5_C3": {"DPS": 70004}, "M4_V2_H3_C3": {"DPS": 69990}, "M1_V1_H5_C5": {"DPS": 69976}, "M7_V0_H2_C3": {"DPS": 69972}, "M0_V5_H7_C0": {"DPS": 69971}, "M4_V1_H3_C4": {"DPS": 69968}, "M7_V1_H2_C2": {"DPS": 69967}, "M2_V3_H4_C3": {"DPS": 69958}, "M4_V3_H3_C2": {"DPS": 69949}, "M7_V2_H2_C1": {"DPS": 69928}, "M0_V4_H6_C2": {"DPS": 69923}, "M8_V0_H2_C2": {"DPS": 69919}, "M5_V4_H3_C0": {"DPS": 69912}, "M1_V4_H5_C2": {"DPS": 69904}, "M6_V1_H2_C3": {"DPS": 69888}, "M3_V5_H4_C0": {"DPS": 69884}, "M6_V2_H2_C2": {"DPS": 69883}, "M2_V1_H4_C5": {"DPS": 69881}, "M4_V0_H3_C5": {"DPS": 69858}, "M8_V1_H2_C1": {"DPS": 69841}, "M2_V4_H4_C2": {"DPS": 69833}, "M6_V0_H2_C4": {"DPS": 69819}, "M0_V0_H6_C6": {"DPS": 69806}, "M6_V3_H2_C1": {"DPS": 69776}, "M7_V3_H2_C0": {"DPS": 69748}, "M2_V0_H4_C6": {"DPS": 69745}, "M1_V0_H5_C6": {"DPS": 69744}, "M4_V4_H3_C1": {"DPS": 69719}, "M8_V2_H2_C0": {"DPS": 69709}, "M5_V2_H2_C3": {"DPS": 69672}, "M5_V1_H2_C4": {"DPS": 69663}, "M1_V5_H5_C1": {"DPS": 69660}, "M0_V5_H6_C1": {"DPS": 69650}, "M9_V0_H2_C1": {"DPS": 69650}, "M3_V2_H3_C4": {"DPS": 69624}, "M5_V3_H2_C2": {"DPS": 69568}, "M2_V5_H4_C1": {"DPS": 69553}, "M9_V1_H2_C0": {"DPS": 69535}, "M3_V3_H3_C3": {"DPS": 69534}, "M3_V1_H3_C5": {"DPS": 69531}, "M6_V4_H2_C0": {"DPS": 69512}, "M5_V0_H2_C5": {"DPS": 69498}, "M3_V4_H3_C2": {"DPS": 69438}, "M5_V4_H2_C1": {"DPS": 69410}, "M4_V5_H3_C0": {"DPS": 69400}, "M1_V3_H4_C4": {"DPS": 69394}, "M4_V2_H2_C4": {"DPS": 69387}, "M1_V2_H4_C5": {"DPS": 69362}, "M4_V3_H2_C3": {"DPS": 69337}, "M3_V0_H3_C6": {"DPS": 69321}, "M0_V3_H5_C4": {"DPS": 69314}, "M1_V6_H5_C0": {"DPS": 69313}, "M1_V4_H4_C3": {"DPS": 69302}, "M10_V0_H2_C0": {"DPS": 69300}, "M0_V2_H5_C5": {"DPS": 69299}, "M0_V6_H6_C0": {"DPS": 69296}, "M4_V1_H2_C5": {"DPS": 69287}, "M0_V4_H5_C3": {"DPS": 69230}, "M4_V4_H2_C2": {"DPS": 69213}, "M2_V6_H4_C0": {"DPS": 69208}, "M3_V5_H3_C1": {"DPS": 69199}, "M1_V1_H4_C6": {"DPS": 69195}, "M4_V0_H2_C6": {"DPS": 69152}, "M0_V1_H5_C6": {"DPS": 69143}, "M5_V5_H2_C0": {"DPS": 69138}, "M1_V5_H4_C2": {"DPS": 69123}, "M2_V3_H3_C4": {"DPS": 69072}, "M0_V5_H5_C2": {"DPS": 69056}, "M2_V2_H3_C5": {"DPS": 69036}, "M4_V5_H2_C1": {"DPS": 68989}, "M2_V4_H3_C3": {"DPS": 68969}, "M7_V1_H1_C3": {"DPS": 68948}, "M1_V0_H4_C7": {"DPS": 68942}, "M0_V0_H5_C7": {"DPS": 68939}, "M3_V3_H2_C4": {"DPS": 68924}, "M7_V2_H1_C2": {"DPS": 68912}, "M3_V2_H2_C5": {"DPS": 68902}, "M3_V4_H2_C3": {"DPS": 68883}, "M2_V1_H3_C6": {"DPS": 68881}, "M7_V0_H1_C4": {"DPS": 68868}, "M6_V2_H1_C3": {"DPS": 68861}, "M8_V1_H1_C2": {"DPS": 68860}, "M1_V6_H4_C1": {"DPS": 68830}, "M3_V6_H3_C0": {"DPS": 68821}, "M8_V0_H1_C3": {"DPS": 68820}, "M2_V5_H3_C2": {"DPS": 68793}, "M6_V1_H1_C4": {"DPS": 68789}, "M7_V3_H1_C1": {"DPS": 68769}, "M3_V1_H2_C6": {"DPS": 68762}, "M0_V6_H5_C1": {"DPS": 68752}, "M8_V2_H1_C1": {"DPS": 68743}, "M6_V3_H1_C2": {"DPS": 68724}, "M6_V0_H1_C5": {"DPS": 68656}, "M2_V0_H3_C7": {"DPS": 68648}, "M9_V0_H1_C2": {"DPS": 68648}, "M3_V5_H2_C2": {"DPS": 68646}, "M4_V6_H2_C0": {"DPS": 68640}, "M9_V1_H1_C1": {"DPS": 68618}, "M0_V3_H4_C5": {"DPS": 68600}, "M5_V2_H1_C4": {"DPS": 68598}, "M5_V3_H1_C3": {"DPS": 68593}, "M0_V4_H4_C4": {"DPS": 68586}, "M7_V4_H1_C0": {"DPS": 68566}, "M8_V3_H1_C0": {"DPS": 68557}, "M6_V4_H1_C1": {"DPS": 68541}, "M3_V0_H2_C7": {"DPS": 68535}, "M0_V2_H4_C6": {"DPS": 68508}, "M5_V1_H1_C5": {"DPS": 68504}, "M2_V6_H3_C1": {"DPS": 68493}, "M9_V2_H1_C0": {"DPS": 68488}, "M0_V5_H4_C3": {"DPS": 68452}, "M5_V4_H1_C2": {"DPS": 68451}, "M1_V7_H4_C0": {"DPS": 68403}, "M1_V3_H3_C5": {"DPS": 68394}, "M3_V6_H2_C1": {"DPS": 68379}, "M1_V4_H3_C4": {"DPS": 68366}, "M10_V0_H1_C1": {"DPS": 68359}, "M2_V3_H2_C5": {"DPS": 68358}, "M0_V7_H5_C0": {"DPS": 68324}, "M2_V2_H2_C6": {"DPS": 68318}, "M2_V4_H2_C4": {"DPS": 68316}, "M5_V0_H1_C6": {"DPS": 68315}, "M0_V1_H4_C7": {"DPS": 68312}, "M1_V2_H3_C6": {"DPS": 68304}, "M6_V5_H1_C0": {"DPS": 68262}, "M4_V3_H1_C4": {"DPS": 68251}, "M10_V1_H1_C0": {"DPS": 68234}, "M5_V5_H1_C1": {"DPS": 68230}, "M1_V5_H3_C3": {"DPS": 68225}, "M0_V6_H4_C2": {"DPS": 68212}, "M4_V2_H1_C5": {"DPS": 68212}, "M2_V5_H2_C3": {"DPS": 68207}, "M4_V4_H1_C3": {"DPS": 68194}, "M1_V1_H3_C7": {"DPS": 68123}, "M4_V1_H1_C6": {"DPS": 68115}, "M2_V1_H2_C7": {"DPS": 68074}, "M2_V7_H3_C0": {"DPS": 68074}, "M4_V5_H1_C2": {"DPS": 68002}, "M1_V6_H3_C2": {"DPS": 67996}, "M2_V6_H2_C2": {"DPS": 67976}, "M3_V7_H2_C0": {"DPS": 67950}, "M0_V0_H4_C8": {"DPS": 67949}, "M4_V0_H1_C7": {"DPS": 67911}, "M5_V6_H1_C0": {"DPS": 67894}, "M7_V2_H0_C3": {"DPS": 67890}, "M7_V1_H0_C4": {"DPS": 67878}, "M0_V7_H4_C1": {"DPS": 67874}, "M3_V3_H1_C5": {"DPS": 67854}, "M8_V1_H0_C3": {"DPS": 67840}, "M7_V3_H0_C2": {"DPS": 67835}, "M3_V4_H1_C4": {"DPS": 67830}, "M11_V0_H1_C0": {"DPS": 67827}, "M8_V2_H0_C2": {"DPS": 67820}, "M3_V2_H1_C6": {"DPS": 67794}, "M7_V0_H0_C5": {"DPS": 67776}, "M8_V0_H0_C4": {"DPS": 67770}, "M4_V6_H1_C1": {"DPS": 67768}, "M3_V5_H1_C3": {"DPS": 67742}, "M1_V0_H3_C8": {"DPS": 67734}, "M2_V0_H2_C8": {"DPS": 67729}, "M6_V2_H0_C4": {"DPS": 67722}, "M6_V3_H0_C3": {"DPS": 67718}, "M9_V1_H0_C2": {"DPS": 67709}, "M1_V4_H2_C5": {"DPS": 67707}, "M1_V7_H3_C1": {"DPS": 67707}, "M8_V3_H0_C1": {"DPS": 67701}, "M2_V7_H2_C1": {"DPS": 67686}, "M0_V3_H3_C6": {"DPS": 67675}, "M6_V1_H0_C5": {"DPS": 67673}, "M0_V4_H3_C5": {"DPS": 67657}, "M7_V4_H0_C1": {"DPS": 67655}, "M1_V3_H2_C6": {"DPS": 67653}, "M9_V0_H0_C3": {"DPS": 67637}, "M9_V2_H0_C1": {"DPS": 67637}, "M1_V5_H2_C4": {"DPS": 67636}, "M6_V4_H0_C2": {"DPS": 67630}, "M3_V1_H1_C7": {"DPS": 67625}, "M1_V2_H2_C7": {"DPS": 67592}, "M0_V5_H3_C4": {"DPS": 67585}, "M5_V3_H0_C4": {"DPS": 67541}, "M6_V0_H0_C6": {"DPS": 67540}, "M0_V2_H3_C7": {"DPS": 67511}, "M3_V6_H1_C2": {"DPS": 67506}, "M8_V4_H0_C0": {"DPS": 67500}, "M5_V2_H0_C5": {"DPS": 67499}, "M1_V6_H2_C3": {"DPS": 67481}, "M10_V0_H0_C2": {"DPS": 67468}, "M0_V6_H3_C3": {"DPS": 67464}, "M4_V7_H1_C0": {"DPS": 67461}, "M5_V4_H0_C3": {"DPS": 67456}, "M10_V1_H0_C1": {"DPS": 67455}, "M9_V3_H0_C0": {"DPS": 67452}, "M7_V5_H0_C0": {"DPS": 67450}, "M6_V5_H0_C1": {"DPS": 67418}, "M0_V8_H4_C0": {"DPS": 67409}, "M5_V1_H0_C6": {"DPS": 67398}, "M2_V4_H1_C5": {"DPS": 67392}, "M2_V3_H1_C6": {"DPS": 67391}, "M3_V0_H1_C8": {"DPS": 67337}, "M5_V5_H0_C2": {"DPS": 67337}, "M2_V5_H1_C4": {"DPS": 67308}, "M3_V7_H1_C1": {"DPS": 67303}, "M10_V2_H0_C0": {"DPS": 67286}, "M1_V1_H2_C8": {"DPS": 67285}, "M1_V7_H2_C2": {"DPS": 67273}, "M0_V1_H3_C8": {"DPS": 67269}, "M1_V8_H3_C0": {"DPS": 67266}, "M0_V7_H3_C2": {"DPS": 67261}, "M2_V2_H1_C7": {"DPS": 67256}, "M4_V3_H0_C5": {"DPS": 67237}, "M4_V4_H0_C4": {"DPS": 67228}, "M5_V0_H0_C7": {"DPS": 67213}, "M2_V6_H1_C3": {"DPS": 67205}, "M2_V8_H2_C0": {"DPS": 67179}, "M4_V2_H0_C6": {"DPS": 67177}, "M4_V5_H0_C3": {"DPS": 67173}, "M6_V6_H0_C0": {"DPS": 67166}, "M5_V6_H0_C1": {"DPS": 67121}, "M11_V0_H0_C1": {"DPS": 67119}, "M4_V1_H0_C7": {"DPS": 67076}, "M0_V4_H2_C6": {"DPS": 67064}, "M0_V5_H2_C5": {"DPS": 67061}, "M11_V1_H0_C0": {"DPS": 67044}, "M2_V7_H1_C2": {"DPS": 67018}, "M2_V1_H1_C8": {"DPS": 67016}, "M0_V3_H2_C7": {"DPS": 67004}, "M4_V6_H0_C2": {"DPS": 66996}, "M1_V0_H2_C9": {"DPS": 66988}, "M0_V6_H2_C4": {"DPS": 66967}, "M3_V4_H0_C5": {"DPS": 66964}, "M0_V0_H3_C9": {"DPS": 66946}, "M0_V8_H3_C1": {"DPS": 66929}, "M1_V4_H1_C6": {"DPS": 66912}, "M1_V8_H2_C1": {"DPS": 66899}, "M3_V3_H0_C6": {"DPS": 66898}, "M5_V7_H0_C0": {"DPS": 66893}, "M3_V8_H1_C0": {"DPS": 66884}, "M1_V5_H1_C5": {"DPS": 66876}, "M3_V5_H0_C4": {"DPS": 66873}, "M1_V3_H1_C7": {"DPS": 66835}, "M0_V7_H2_C3": {"DPS": 66812}, "M3_V2_H0_C7": {"DPS": 66805}, "M4_V0_H0_C8": {"DPS": 66784}, "M4_V7_H0_C1": {"DPS": 66777}, "M1_V6_H1_C4": {"DPS": 66770}, "M0_V2_H2_C8": {"DPS": 66762}, "M3_V6_H0_C3": {"DPS": 66739}, "M12_V0_H0_C0": {"DPS": 66706}, "M2_V8_H1_C1": {"DPS": 66676}, "M2_V0_H1_C9": {"DPS": 66675}, "M1_V2_H1_C8": {"DPS": 66637}, "M1_V7_H1_C3": {"DPS": 66603}, "M3_V1_H0_C8": {"DPS": 66542}, "M3_V7_H0_C2": {"DPS": 66527}, "M0_V8_H2_C2": {"DPS": 66518}, "M2_V4_H0_C6": {"DPS": 66493}, "M0_V9_H3_C0": {"DPS": 66474}, "M1_V9_H2_C0": {"DPS": 66465}, "M2_V5_H0_C5": {"DPS": 66465}, "M0_V1_H2_C9": {"DPS": 66437}, "M2_V3_H0_C7": {"DPS": 66431}, "M2_V6_H0_C4": {"DPS": 66385}, "M4_V8_H0_C0": {"DPS": 66372}, "M1_V8_H1_C2": {"DPS": 66263}, "M0_V5_H1_C6": {"DPS": 66250}, "M1_V1_H1_C9": {"DPS": 66240}, "M0_V4_H1_C7": {"DPS": 66224}, "M2_V7_H0_C3": {"DPS": 66216}, "M2_V2_H0_C8": {"DPS": 66202}, "M3_V8_H0_C1": {"DPS": 66178}, "M2_V9_H1_C0": {"DPS": 66172}, "M0_V6_H1_C5": {"DPS": 66166}, "M3_V0_H0_C9": {"DPS": 66161}, "M0_V9_H2_C1": {"DPS": 66011}, "M0_V7_H1_C4": {"DPS": 65998}, "M0_V3_H1_C8": {"DPS": 65988}, "M0_V0_H2_C10": {"DPS": 65987}, "M1_V4_H0_C7": {"DPS": 65882}, "M1_V5_H0_C6": {"DPS": 65851}, "M2_V8_H0_C2": {"DPS": 65827}, "M1_V6_H0_C5": {"DPS": 65807}, "M2_V1_H0_C9": {"DPS": 65785}, "M1_V9_H1_C1": {"DPS": 65744}, "M1_V0_H1_C10": {"DPS": 65708}, "M1_V7_H0_C4": {"DPS": 65671}, "M0_V8_H1_C3": {"DPS": 65650}, "M3_V9_H0_C0": {"DPS": 65618}, "M1_V3_H0_C8": {"DPS": 65613}, "M0_V2_H1_C9": {"DPS": 65571}, "M0_V10_H2_C0": {"DPS": 65430}, "M2_V9_H0_C1": {"DPS": 65314}, "M1_V8_H0_C3": {"DPS": 65310}, "M2_V0_H0_C10": {"DPS": 65274}, "M1_V2_H0_C9": {"DPS": 65239}, "M0_V9_H1_C2": {"DPS": 65132}, "M1_V10_H1_C0": {"DPS": 65114}, "M0_V5_H0_C7": {"DPS": 65072}, "M0_V1_H1_C10": {"DPS": 65061}, "M0_V6_H0_C6": {"DPS": 64996}, "M0_V7_H0_C5": {"DPS": 64913}, "M0_V4_H0_C8": {"DPS": 64830}, "M1_V9_H0_C2": {"DPS": 64829}, "M1_V1_H0_C10": {"DPS": 64762}, "M2_V10_H0_C0": {"DPS": 64621}, "M0_V8_H0_C4": {"DPS": 64584}, "M0_V10_H1_C1": {"DPS": 64568}, "M0_V3_H0_C9": {"DPS": 64498}, "M0_V0_H1_C11": {"DPS": 64370}, "M1_V10_H0_C1": {"DPS": 64233}, "M0_V9_H0_C3": {"DPS": 64146}, "M0_V2_H0_C10": {"DPS": 64072}, "M1_V0_H0_C11": {"DPS": 64054}, "M0_V11_H1_C0": {"DPS": 63811}, "M0_V10_H0_C2": {"DPS": 63651}, "M1_V11_H0_C0": {"DPS": 63465}, "M0_V1_H0_C11": {"DPS": 63462}, "M0_V11_H0_C1": {"DPS": 63094}, "M0_V0_H0_C12": {"DPS": 62931}, "M0_V12_H0_C0": {"DPS": 62591}, "Base": {"DPS": 47302}}, "ids": {"M5_V0_H7_C0": null, "M4_V0_H8_C0": null, "M4_V0_H7_C1": null, "M3_V0_H9_C0": null, "M6_V0_H6_C0": null, "M4_V1_H7_C0": null, "M3_V0_H8_C1": null, "M5_V0_H6_C1": null, "M3_V1_H8_C0": null, "M3_V0_H7_C2": null, "M5_V1_H6_C0": null, "M3_V1_H7_C1": null, "M4_V0_H6_C2": null, "M2_V0_H9_C1": null, "M3_V2_H7_C0": null, "M4_V1_H6_C1": null, "M2_V1_H9_C0": null, "M2_V0_H8_C2": null, "M2_V1_H8_C1": null, "M4_V2_H6_C0": null, "M6_V0_H5_C1": null, "M7_V0_H5_C0": null, "M2_V2_H8_C0": null, "M2_V1_H7_C2": null, "M3_V1_H6_C2": null, "M2_V0_H7_C3": null, "M2_V0_H10_C0": null, "M6_V1_H5_C0": null, "M3_V0_H6_C3": null, "M2_V2_H7_C1": null, "M5_V0_H5_C2": null, "M5_V1_H5_C1": null, "M3_V2_H6_C1": null, "M1_V1_H9_C1": null, "M1_V0_H9_C2": null, "M5_V2_H5_C0": null, "M2_V3_H7_C0": null, "M4_V1_H5_C2": null, "M1_V1_H8_C2": null, "M3_V3_H6_C0": null, "M1_V0_H8_C3": null, "M4_V0_H5_C3": null, "M1_V2_H9_C0": null, "M1_V2_H8_C1": null, "M4_V2_H5_C1": null, "M2_V2_H6_C2": null, "M1_V0_H10_C1": null, "M7_V0_H4_C1": null, "M2_V1_H6_C3": null, "M1_V0_H11_C0": null, "M6_V0_H4_C2": null, "M7_V1_H4_C0": null, "M2_V0_H6_C4": null, "M1_V1_H7_C3": null, "M1_V2_H7_C2": null, "M6_V1_H4_C1": null, "M1_V1_H10_C0": null, "M1_V3_H8_C0": null, "M4_V3_H5_C0": null, "M2_V3_H6_C1": null, "M1_V0_H7_C4": null, "M3_V1_H5_C3": null, "M8_V0_H4_C0": null, "M6_V2_H4_C0": null, "M3_V2_H5_C2": null, "M1_V3_H7_C1": null, "M5_V1_H4_C2": null, "M5_V0_H4_C3": null, "M3_V0_H5_C4": null, "M5_V2_H4_C1": null, "M3_V3_H5_C1": null, "M0_V1_H9_C2": null, "M0_V0_H9_C3": null, "M2_V4_H6_C0": null, "M0_V2_H9_C1": null, "M4_V1_H4_C3": null, "M0_V1_H8_C3": null, "M5_V3_H4_C0": null, "M0_V2_H8_C2": null, "M1_V2_H6_C3": null, "M1_V4_H7_C0": null, "M4_V2_H4_C2": null, "M4_V0_H4_C4": null, "M0_V0_H8_C4": null, "M1_V1_H6_C4": null, "M0_V0_H10_C2": null, "M0_V0_H11_C1": null, "M1_V3_H6_C2": null, "M0_V1_H10_C1": null, "M0_V3_H8_C1": null, "M0_V3_H9_C0": null, "M0_V1_H11_C0": null, "M3_V4_H5_C0": null, "M2_V2_H5_C3": null, "M7_V0_H3_C2": null, "M4_V3_H4_C1": null, "M2_V1_H5_C4": null, "M1_V0_H6_C5": null, "M7_V1_H3_C1": null, "M2_V3_H5_C2": null, "M0_V2_H10_C0": null, "M0_V2_H7_C3": null, "M0_V1_H7_C4": null, "M6_V1_H3_C2": null, "M6_V0_H3_C3": null, "M1_V4_H6_C1": null, "M2_V0_H5_C5": null, "M0_V3_H7_C2": null, "M3_V2_H4_C3": null, "M3_V1_H4_C4": null, "M8_V0_H3_C1": null, "M4_V4_H4_C0": null, "M7_V2_H3_C0": null, "M6_V2_H3_C1": null, "M0_V4_H8_C0": null, "M0_V0_H7_C5": null, "M2_V4_H5_C1": null, "M8_V1_H3_C0": null, "M3_V3_H4_C2": null, "M3_V0_H4_C5": null, "M5_V2_H3_C2": null, "M5_V1_H3_C3": null, "M0_V4_H7_C1": null, "M6_V3_H3_C0": null, "M0_V0_H12_C0": null, "M5_V0_H3_C4": null, "M3_V4_H4_C1": null, "M1_V5_H6_C0": null, "M5_V3_H3_C1": null, "M9_V0_H3_C0": null, "M0_V2_H6_C4": null, "M2_V5_H5_C0": null, "M1_V2_H5_C4": null, "M0_V3_H6_C3": null, "M2_V2_H4_C4": null, "M0_V1_H6_C5": null, "M1_V3_H5_C3": null, "M4_V2_H3_C3": null, "M1_V1_H5_C5": null, "M7_V0_H2_C3": null, "M0_V5_H7_C0": null, "M4_V1_H3_C4": null, "M7_V1_H2_C2": null, "M2_V3_H4_C3": null, "M4_V3_H3_C2": null, "M7_V2_H2_C1": null, "M0_V4_H6_C2": null, "M8_V0_H2_C2": null, "M5_V4_H3_C0": null, "M1_V4_H5_C2": null, "M6_V1_H2_C3": null, "M3_V5_H4_C0": null, "M6_V2_H2_C2": null, "M2_V1_H4_C5": null, "M4_V0_H3_C5": null, "M8_V1_H2_C1": null, "M2_V4_H4_C2": null, "M6_V0_H2_C4": null, "M0_V0_H6_C6": null, "M6_V3_H2_C1": null, "M7_V3_H2_C0": null, "M2_V0_H4_C6": null, "M1_V0_H5_C6": null, "M4_V4_H3_C1": null, "M8_V2_H2_C0": null, "M5_V2_H2_C3": null, "M5_V1_H2_C4": null, "M1_V5_H5_C1": null, "M0_V5_H6_C1": null, "M9_V0_H2_C1": null, "M3_V2_H3_C4": null, "M5_V3_H2_C2": null, "M2_V5_H4_C1": null, "M9_V1_H2_C0": null, "M3_V3_H3_C3": null, "M3_V1_H3_C5": null, "M6_V4_H2_C0": null, "M5_V0_H2_C5": null, "M3_V4_H3_C2": null, "M5_V4_H2_C1": null, "M4_V5_H3_C0": null, "M1_V3_H4_C4": null, "M4_V2_H2_C4": null, "M1_V2_H4_C5": null, "M4_V3_H2_C3": null, "M3_V0_H3_C6": null, "M0_V3_H5_C4": null, "M1_V6_H5_C0": null, "M1_V4_H4_C3": null, "M10_V0_H2_C0": null, "M0_V2_H5_C5": null, "M0_V6_H6_C0": null, "M4_V1_H2_C5": null, "M0_V4_H5_C3": null, "M4_V4_H2_C2": null, "M2_V6_H4_C0": null, "M3_V5_H3_C1": null, "M1_V1_H4_C6": null, "M4_V0_H2_C6": null, "M0_V1_H5_C6": null, "M5_V5_H2_C0": null, "M1_V5_H4_C2": null, "M2_V3_H3_C4": null, "M0_V5_H5_C2": null, "M2_V2_H3_C5": null, "M4_V5_H2_C1": null, "M2_V4_H3_C3": null, "M7_V1_H1_C3": null, "M1_V0_H4_C7": null, "M0_V0_H5_C7": null, "M3_V3_H2_C4": null, "M7_V2_H1_C2": null, "M3_V2_H2_C5": null, "M3_V4_H2_C3": null, "M2_V1_H3_C6": null, "M7_V0_H1_C4": null, "M6_V2_H1_C3": null, "M8_V1_H1_C2": null, "M1_V6_H4_C1": null, "M3_V6_H3_C0": null, "M8_V0_H1_C3": null, "M2_V5_H3_C2": null, "M6_V1_H1_C4": null, "M7_V3_H1_C1": null, "M3_V1_H2_C6": null, "M0_V6_H5_C1": null, "M8_V2_H1_C1": null, "M6_V3_H1_C2": null, "M6_V0_H1_C5": null, "M2_V0_H3_C7": null, "M9_V0_H1_C2": null, "M3_V5_H2_C2": null, "M4_V6_H2_C0": null, "M9_V1_H1_C1": null, "M0_V3_H4_C5": null, "M5_V2_H1_C4": null, "M5_V3_H1_C3": null, "M0_V4_H4_C4": null, "M7_V4_H1_C0": null, "M8_V3_H1_C0": null, "M6_V4_H1_C1": null, "M3_V0_H2_C7": null, "M0_V2_H4_C6": null, "M5_V1_H1_C5": null, "M2_V6_H3_C1": null, "M9_V2_H1_C0": null, "M0_V5_H4_C3": null, "M5_V4_H1_C2": null, "M1_V7_H4_C0": null, "M1_V3_H3_C5": null, "M3_V6_H2_C1": null, "M1_V4_H3_C4": null, "M10_V0_H1_C1": null, "M2_V3_H2_C5": null, "M0_V7_H5_C0": null, "M2_V2_H2_C6": null, "M2_V4_H2_C4": null, "M5_V0_H1_C6": null, "M0_V1_H4_C7": null, "M1_V2_H3_C6": null, "M6_V5_H1_C0": null, "M4_V3_H1_C4": null, "M10_V1_H1_C0": null, "M5_V5_H1_C1": null, "M1_V5_H3_C3": null, "M0_V6_H4_C2": null, "M4_V2_H1_C5": null, "M2_V5_H2_C3": null, "M4_V4_H1_C3": null, "M1_V1_H3_C7": null, "M4_V1_H1_C6": null, "M2_V1_H2_C7": null, "M2_V7_H3_C0": null, "M4_V5_H1_C2": null, "M1_V6_H3_C2": null, "M2_V6_H2_C2": null, "M3_V7_H2_C0": null, "M0_V0_H4_C8": null, "M4_V0_H1_C7": null, "M5_V6_H1_C0": null, "M7_V2_H0_C3": null, "M7_V1_H0_C4": null, "M0_V7_H4_C1": null, "M3_V3_H1_C5": null, "M8_V1_H0_C3": null, "M7_V3_H0_C2": null, "M3_V4_H1_C4": null, "M11_V0_H1_C0": null, "M8_V2_H0_C2": null, "M3_V2_H1_C6": null, "M7_V0_H0_C5": null, "M8_V0_H0_C4": null, "M4_V6_H1_C1": null, "M3_V5_H1_C3": null, "M1_V0_H3_C8": null, "M2_V0_H2_C8": null, "M6_V2_H0_C4": null, "M6_V3_H0_C3": null, "M9_V1_H0_C2": null, "M1_V4_H2_C5": null, "M1_V7_H3_C1": null, "M8_V3_H0_C1": null, "M2_V7_H2_C1": null, "M0_V3_H3_C6": null, "M6_V1_H0_C5": null, "M0_V4_H3_C5": null, "M7_V4_H0_C1": null, "M1_V3_H2_C6": null, "M9_V0_H0_C3": null, "M9_V2_H0_C1": null, "M1_V5_H2_C4": null, "M6_V4_H0_C2": null, "M3_V1_H1_C7": null, "M1_V2_H2_C7": null, "M0_V5_H3_C4": null, "M5_V3_H0_C4": null, "M6_V0_H0_C6": null, "M0_V2_H3_C7": null, "M3_V6_H1_C2": null, "M8_V4_H0_C0": null, "M5_V2_H0_C5": null, "M1_V6_H2_C3": null, "M10_V0_H0_C2": null, "M0_V6_H3_C3": null, "M4_V7_H1_C0": null, "M5_V4_H0_C3": null, "M10_V1_H0_C1": null, "M9_V3_H0_C0": null, "M7_V5_H0_C0": null, "M6_V5_H0_C1": null, "M0_V8_H4_C0": null, "M5_V1_H0_C6": null, "M2_V4_H1_C5": null, "M2_V3_H1_C6": null, "M3_V0_H1_C8": null, "M5_V5_H0_C2": null, "M2_V5_H1_C4": null, "M3_V7_H1_C1": null, "M10_V2_H0_C0": null, "M1_V1_H2_C8": null, "M1_V7_H2_C2": null, "M0_V1_H3_C8": null, "M1_V8_H3_C0": null, "M0_V7_H3_C2": null, "M2_V2_H1_C7": null, "M4_V3_H0_C5": null, "M4_V4_H0_C4": null, "M5_V0_H0_C7": null, "M2_V6_H1_C3": null, "M2_V8_H2_C0": null, "M4_V2_H0_C6": null, "M4_V5_H0_C3": null, "M6_V6_H0_C0": null, "M5_V6_H0_C1": null, "M11_V0_H0_C1": null, "M4_V1_H0_C7": null, "M0_V4_H2_C6": null, "M0_V5_H2_C5": null, "M11_V1_H0_C0": null, "M2_V7_H1_C2": null, "M2_V1_H1_C8": null, "M0_V3_H2_C7": null, "M4_V6_H0_C2": null, "M1_V0_H2_C9": null, "M0_V6_H2_C4": null, "M3_V4_H0_C5": null, "M0_V0_H3_C9": null, "M0_V8_H3_C1": null, "M1_V4_H1_C6": null, "M1_V8_H2_C1": null, "M3_V3_H0_C6": null, "M5_V7_H0_C0": null, "M3_V8_H1_C0": null, "M1_V5_H1_C5": null, "M3_V5_H0_C4": null, "M1_V3_H1_C7": null, "M0_V7_H2_C3": null, "M3_V2_H0_C7": null, "M4_V0_H0_C8": null, "M4_V7_H0_C1": null, "M1_V6_H1_C4": null, "M0_V2_H2_C8": null, "M3_V6_H0_C3": null, "M12_V0_H0_C0": null, "M2_V8_H1_C1": null, "M2_V0_H1_C9": null, "M1_V2_H1_C8": null, "M1_V7_H1_C3": null, "M3_V1_H0_C8": null, "M3_V7_H0_C2": null, "M0_V8_H2_C2": null, "M2_V4_H0_C6": null, "M0_V9_H3_C0": null, "M1_V9_H2_C0": null, "M2_V5_H0_C5": null, "M0_V1_H2_C9": null, "M2_V3_H0_C7": null, "M2_V6_H0_C4": null, "M4_V8_H0_C0": null, "M1_V8_H1_C2": null, "M0_V5_H1_C6": null, "M1_V1_H1_C9": null, "M0_V4_H1_C7": null, "M2_V7_H0_C3": null, "M2_V2_H0_C8": null, "M3_V8_H0_C1": null, "M2_V9_H1_C0": null, "M0_V6_H1_C5": null, "M3_V0_H0_C9": null, "M0_V9_H2_C1": null, "M0_V7_H1_C4": null, "M0_V3_H1_C8": null, "M0_V0_H2_C10": null, "M1_V4_H0_C7": null, "M1_V5_H0_C6": null, "M2_V8_H0_C2": null, "M1_V6_H0_C5": null, "M2_V1_H0_C9": null, "M1_V9_H1_C1": null, "M1_V0_H1_C10": null, "M1_V7_H0_C4": null, "M0_V8_H1_C3": null, "M3_V9_H0_C0": null, "M1_V3_H0_C8": null, "M0_V2_H1_C9": null, "M0_V10_H2_C0": null, "M2_V9_H0_C1": null, "M1_V8_H0_C3": null, "M2_V0_H0_C10": null, "M1_V2_H0_C9": null, "M0_V9_H1_C2": null, "M1_V10_H1_C0": null, "M0_V5_H0_C7": null, "M0_V1_H1_C10": null, "M0_V6_H0_C6": null, "M0_V7_H0_C5": null, "M0_V4_H0_C8": null, "M1_V9_H0_C2": null, "M1_V1_H0_C10": null, "M2_V10_H0_C0": null, "M0_V8_H0_C4": null, "M0_V10_H1_C1": null, "M0_V3_H0_C9": null, "M0_V0_H1_C11": null, "M1_V10_H0_C1": null, "M0_V9_H0_C3": null, "M0_V2_H0_C10": null, "M1_V0_H0_C11": null, "M0_V11_H1_C0": null, "M0_V10_H0_C2": null, "M1_V11_H0_C0": null, "M0_V1_H0_C11": null, "M0_V11_H0_C1": null, "M0_V0_H0_C12": null, "M0_V12_H0_C0": null}, "simulated_steps": ["DPS"], "sorted_data_keys": ["M5_V0_H7_C0", "M4_V0_H8_C0", "M4_V0_H7_C1", "M3_V0_H9_C0", "M6_V0_H6_C0", "M4_V1_H7_C0", "M3_V0_H8_C1", "M5_V0_H6_C1", "M3_V1_H8_C0", "M3_V0_H7_C2", "M5_V1_H6_C0", "M3_V1_H7_C1", "M4_V0_H6_C2", "M2_V0_H9_C1", "M3_V2_H7_C0", "M4_V1_H6_C1", "M2_V1_H9_C0", "M2_V0_H8_C2", "M2_V1_H8_C1", "M4_V2_H6_C0", "M6_V0_H5_C1", "M7_V0_H5_C0", "M2_V2_H8_C0", "M2_V1_H7_C2", "M3_V1_H6_C2", "M2_V0_H7_C3", "M2_V0_H10_C0", "M6_V1_H5_C0", "M3_V0_H6_C3", "M2_V2_H7_C1", "M5_V0_H5_C2", "M5_V1_H5_C1", "M3_V2_H6_C1", "M1_V1_H9_C1", "M1_V0_H9_C2", "M5_V2_H5_C0", "M2_V3_H7_C0", "M4_V1_H5_C2", "M1_V1_H8_C2", "M3_V3_H6_C0", "M1_V0_H8_C3", "M4_V0_H5_C3", "M1_V2_H9_C0", "M1_V2_H8_C1", "M4_V2_H5_C1", "M2_V2_H6_C2", "M1_V0_H10_C1", "M7_V0_H4_C1", "M2_V1_H6_C3", "M1_V0_H11_C0", "M6_V0_H4_C2", "M7_V1_H4_C0", "M2_V0_H6_C4", "M1_V1_H7_C3", "M1_V2_H7_C2", "M6_V1_H4_C1", "M1_V1_H10_C0", "M1_V3_H8_C0", "M4_V3_H5_C0", "M2_V3_H6_C1", "M1_V0_H7_C4", "M3_V1_H5_C3", "M8_V0_H4_C0", "M6_V2_H4_C0", "M3_V2_H5_C2", "M1_V3_H7_C1", "M5_V1_H4_C2", "M5_V0_H4_C3", "M3_V0_H5_C4", "M5_V2_H4_C1", "M3_V3_H5_C1", "M0_V1_H9_C2", "M0_V0_H9_C3", "M2_V4_H6_C0", "M0_V2_H9_C1", "M4_V1_H4_C3", "M0_V1_H8_C3", "M5_V3_H4_C0", "M0_V2_H8_C2", "M1_V2_H6_C3", "M1_V4_H7_C0", "M4_V2_H4_C2", "M4_V0_H4_C4", "M0_V0_H8_C4", "M1_V1_H6_C4", "M0_V0_H10_C2", "M0_V0_H11_C1", "M1_V3_H6_C2", "M0_V1_H10_C1", "M0_V3_H8_C1", "M0_V3_H9_C0", "M0_V1_H11_C0", "M3_V4_H5_C0", "M2_V2_H5_C3", "M7_V0_H3_C2", "M4_V3_H4_C1", "M2_V1_H5_C4", "M1_V0_H6_C5", "M7_V1_H3_C1", "M2_V3_H5_C2", "M0_V2_H10_C0", "M0_V2_H7_C3", "M0_V1_H7_C4", "M6_V1_H3_C2", "M6_V0_H3_C3", "M1_V4_H6_C1", "M2_V0_H5_C5", "M0_V3_H7_C2", "M3_V2_H4_C3", "M3_V1_H4_C4", "M8_V0_H3_C1", "M4_V4_H4_C0", "M7_V2_H3_C0", "M6_V2_H3_C1", "M0_V4_H8_C0", "M0_V0_H7_C5", "M2_V4_H5_C1", "M8_V1_H3_C0", "M3_V3_H4_C2", "M3_V0_H4_C5", "M5_V2_H3_C2", "M5_V1_H3_C3", "M0_V4_H7_C1", "M6_V3_H3_C0", "M0_V0_H12_C0", "M5_V0_H3_C4", "M3_V4_H4_C1", "M1_V5_H6_C0", "M5_V3_H3_C1", "M9_V0_H3_C0", "M0_V2_H6_C4", "M2_V5_H5_C0", "M1_V2_H5_C4", "M0_V3_H6_C3", "M2_V2_H4_C4", "M0_V1_H6_C5", "M1_V3_H5_C3", "M4_V2_H3_C3", "M1_V1_H5_C5", "M7_V0_H2_C3", "M0_V5_H7_C0", "M4_V1_H3_C4", "M7_V1_H2_C2", "M2_V3_H4_C3", "M4_V3_H3_C2", "M7_V2_H2_C1", "M0_V4_H6_C2", "M8_V0_H2_C2", "M5_V4_H3_C0", "M1_V4_H5_C2", "M6_V1_H2_C3", "M3_V5_H4_C0", "M6_V2_H2_C2", "M2_V1_H4_C5", "M4_V0_H3_C5", "M8_V1_H2_C1", "M2_V4_H4_C2", "M6_V0_H2_C4", "M0_V0_H6_C6", "M6_V3_H2_C1", "M7_V3_H2_C0", "M2_V0_H4_C6", "M1_V0_H5_C6", "M4_V4_H3_C1", "M8_V2_H2_C0", "M5_V2_H2_C3", "M5_V1_H2_C4", "M1_V5_H5_C1", "M0_V5_H6_C1", "M9_V0_H2_C1", "M3_V2_H3_C4", "M5_V3_H2_C2", "M2_V5_H4_C1", "M9_V1_H2_C0", "M3_V3_H3_C3", "M3_V1_H3_C5", "M6_V4_H2_C0", "M5_V0_H2_C5", "M3_V4_H3_C2", "M5_V4_H2_C1", "M4_V5_H3_C0", "M1_V3_H4_C4", "M4_V2_H2_C4", "M1_V2_H4_C5", "M4_V3_H2_C3", "M3_V0_H3_C6", "M0_V3_H5_C4", "M1_V6_H5_C0", "M1_V4_H4_C3", "M10_V0_H2_C0", "M0_V2_H5_C5", "M0_V6_H6_C0", "M4_V1_H2_C5", "M0_V4_H5_C3", "M4_V4_H2_C2", "M2_V6_H4_C0", "M3_V5_H3_C1", "M1_V1_H4_C6", "M4_V0_H2_C6", "M0_V1_H5_C6", "M5_V5_H2_C0", "M1_V5_H4_C2", "M2_V3_H3_C4", "M0_V5_H5_C2", "M2_V2_H3_C5", "M4_V5_H2_C1", "M2_V4_H3_C3", "M7_V1_H1_C3", "M1_V0_H4_C7", "M0_V0_H5_C7", "M3_V3_H2_C4", "M7_V2_H1_C2", "M3_V2_H2_C5", "M3_V4_H2_C3", "M2_V1_H3_C6", "M7_V0_H1_C4", "M6_V2_H1_C3", "M8_V1_H1_C2", "M1_V6_H4_C1", "M3_V6_H3_C0", "M8_V0_H1_C3", "M2_V5_H3_C2", "M6_V1_H1_C4", "M7_V3_H1_C1", "M3_V1_H2_C6", "M0_V6_H5_C1", "M8_V2_H1_C1", "M6_V3_H1_C2", "M6_V0_H1_C5", "M2_V0_H3_C7", "M9_V0_H1_C2", "M3_V5_H2_C2", "M4_V6_H2_C0", "M9_V1_H1_C1", "M0_V3_H4_C5", "M5_V2_H1_C4", "M5_V3_H1_C3", "M0_V4_H4_C4", "M7_V4_H1_C0", "M8_V3_H1_C0", "M6_V4_H1_C1", "M3_V0_H2_C7", "M0_V2_H4_C6", "M5_V1_H1_C5", "M2_V6_H3_C1", "M9_V2_H1_C0", "M0_V5_H4_C3", "M5_V4_H1_C2", "M1_V7_H4_C0", "M1_V3_H3_C5", "M3_V6_H2_C1", "M1_V4_H3_C4", "M10_V0_H1_C1", "M2_V3_H2_C5", "M0_V7_H5_C0", "M2_V2_H2_C6", "M2_V4_H2_C4", "M5_V0_H1_C6", "M0_V1_H4_C7", "M1_V2_H3_C6", "M6_V5_H1_C0", "M4_V3_H1_C4", "M10_V1_H1_C0", "M5_V5_H1_C1", "M1_V5_H3_C3", "M0_V6_H4_C2", "M4_V2_H1_C5", "M2_V5_H2_C3", "M4_V4_H1_C3", "M1_V1_H3_C7", "M4_V1_H1_C6", "M2_V1_H2_C7", "M2_V7_H3_C0", "M4_V5_H1_C2", "M1_V6_H3_C2", "M2_V6_H2_C2", "M3_V7_H2_C0", "M0_V0_H4_C8", "M4_V0_H1_C7", "M5_V6_H1_C0", "M7_V2_H0_C3", "M7_V1_H0_C4", "M0_V7_H4_C1", "M3_V3_H1_C5", "M8_V1_H0_C3", "M7_V3_H0_C2", "M3_V4_H1_C4", "M11_V0_H1_C0", "M8_V2_H0_C2", "M3_V2_H1_C6", "M7_V0_H0_C5", "M8_V0_H0_C4", "M4_V6_H1_C1", "M3_V5_H1_C3", "M1_V0_H3_C8", "M2_V0_H2_C8", "M6_V2_H0_C4", "M6_V3_H0_C3", "M9_V1_H0_C2", "M1_V4_H2_C5", "M1_V7_H3_C1", "M8_V3_H0_C1", "M2_V7_H2_C1", "M0_V3_H3_C6", "M6_V1_H0_C5", "M0_V4_H3_C5", "M7_V4_H0_C1", "M1_V3_H2_C6", "M9_V0_H0_C3", "M9_V2_H0_C1", "M1_V5_H2_C4", "M6_V4_H0_C2", "M3_V1_H1_C7", "M1_V2_H2_C7", "M0_V5_H3_C4", "M5_V3_H0_C4", "M6_V0_H0_C6", "M0_V2_H3_C7", "M3_V6_H1_C2", "M8_V4_H0_C0", "M5_V2_H0_C5", "M1_V6_H2_C3", "M10_V0_H0_C2", "M0_V6_H3_C3", "M4_V7_H1_C0", "M5_V4_H0_C3", "M10_V1_H0_C1", "M9_V3_H0_C0", "M7_V5_H0_C0", "M6_V5_H0_C1", "M0_V8_H4_C0", "M5_V1_H0_C6", "M2_V4_H1_C5", "M2_V3_H1_C6", "M3_V0_H1_C8", "M5_V5_H0_C2", "M2_V5_H1_C4", "M3_V7_H1_C1", "M10_V2_H0_C0", "M1_V1_H2_C8", "M1_V7_H2_C2", "M0_V1_H3_C8", "M1_V8_H3_C0", "M0_V7_H3_C2", "M2_V2_H1_C7", "M4_V3_H0_C5", "M4_V4_H0_C4", "M5_V0_H0_C7", "M2_V6_H1_C3", "M2_V8_H2_C0", "M4_V2_H0_C6", "M4_V5_H0_C3", "M6_V6_H0_C0", "M5_V6_H0_C1", "M11_V0_H0_C1", "M4_V1_H0_C7", "M0_V4_H2_C6", "M0_V5_H2_C5", "M11_V1_H0_C0", "M2_V7_H1_C2", "M2_V1_H1_C8", "M0_V3_H2_C7", "M4_V6_H0_C2", "M1_V0_H2_C9", "M0_V6_H2_C4", "M3_V4_H0_C5", "M0_V0_H3_C9", "M0_V8_H3_C1", "M1_V4_H1_C6", "M1_V8_H2_C1", "M3_V3_H0_C6", "M5_V7_H0_C0", "M3_V8_H1_C0", "M1_V5_H1_C5", "M3_V5_H0_C4", "M1_V3_H1_C7", "M0_V7_H2_C3", "M3_V2_H0_C7", "M4_V0_H0_C8", "M4_V7_H0_C1", "M1_V6_H1_C4", "M0_V2_H2_C8", "M3_V6_H0_C3", "M12_V0_H0_C0", "M2_V8_H1_C1", "M2_V0_H1_C9", "M1_V2_H1_C8", "M1_V7_H1_C3", "M3_V1_H0_C8", "M3_V7_H0_C2", "M0_V8_H2_C2", "M2_V4_H0_C6", "M0_V9_H3_C0", "M1_V9_H2_C0", "M2_V5_H0_C5", "M0_V1_H2_C9", "M2_V3_H0_C7", "M2_V6_H0_C4", "M4_V8_H0_C0", "M1_V8_H1_C2", "M0_V5_H1_C6", "M1_V1_H1_C9", "M0_V4_H1_C7", "M2_V7_H0_C3", "M2_V2_H0_C8", "M3_V8_H0_C1", "M2_V9_H1_C0", "M0_V6_H1_C5", "M3_V0_H0_C9", "M0_V9_H2_C1", "M0_V7_H1_C4", "M0_V3_H1_C8", "M0_V0_H2_C10", "M1_V4_H0_C7", "M1_V5_H0_C6", "M2_V8_H0_C2", "M1_V6_H0_C5", "M2_V1_H0_C9", "M1_V9_H1_C1", "M1_V0_H1_C10", "M1_V7_H0_C4", "M0_V8_H1_C3", "M3_V9_H0_C0", "M1_V3_H0_C8", "M0_V2_H1_C9", "M0_V10_H2_C0", "M2_V9_H0_C1", "M1_V8_H0_C3", "M2_V0_H0_C10", "M1_V2_H0_C9", "M0_V9_H1_C2", "M1_V10_H1_C0", "M0_V5_H0_C7", "M0_V1_H1_C10", "M0_V6_H0_C6", "M0_V7_H0_C5", "M0_V4_H0_C8", "M1_V9_H0_C2", "M1_V1_H0_C10", "M2_V10_H0_C0", "M0_V8_H0_C4", "M0_V10_H1_C1", "M0_V3_H0_C9", "M0_V0_H1_C11", "M1_V10_H0_C1", "M0_V9_H0_C3", "M0_V2_H0_C10", "M1_V0_H0_C11", "M0_V11_H1_C0", "M0_V10_H0_C2", "M1_V11_H0_C0", "M0_V1_H0_C11", "M0_V11_H0_C1", "M0_V0_H0_C12", "M0_V12_H0_C0"], "last_updated": "2023-02-07"}